{"UTF8Encoding":true,"type":"FeatureCollection","features":[{"type":"Feature","id":"520402001","properties":{"name":"南街街道办事处","childNum":3,"cp":[105.940695,26.249955]},"geometry":{"type":"MultiPolygon","coordinates":[["@@AGECQBUBGA@OOGCKPCVDXAPIDI@@BABABAFCLEFCDEAAEAE@C@CAECCGAGBEA@@@@C@@@A@A@C@AAA@A@A@ABA@A@@@A@CA@@A@AA@@A@A@@@AAA@A@@AA@C@A@C@AA@@A@A@CA@AC@AAA@C@@@A@AAA@@@AA@AA@@A@@BA@@B@@A@AAAAACEAGACACAAC@CBCFAHAPBH@@@B@@@@@@@FABABC@A@@@AB@@A@@@@LMDOEIKGKIIGOFENEFMAGOCYC[AKCSAC@AA@@@A@CKACAAA@C@C@@AACAA@CBA@@B@GI@BCDA@A@A@A@AB@BA@@@A@@CAACI@C@CB@BAD@D@@@AE@A@CBABABA@C@CBADGAAACC@C@A@@@BA@C@AAA@E@@D@D@@@BC@C@EACAAA@AB@BAB@D@@ABA@@@@BA@ACC@A@CACAA@C@A@C@@A@@BA@@AAA@A@A@@A@A@AAE@A@C@G@EAAAAAAC@CBAB@@A@@@@B@BABA@CAABA@@E@IBEAAAAA@@A@ADCB@D@@A@C@ACAAAADAB@B@BCA@@A@A@@ABA@A@A@@C@CCAIECIBCH@L@NANATATCLIPKLOHQFKDQBOCIAGDAFEJCHEHCLGHGJQ@MAIEQGIIKKGKECAACCECAAA@@A@CAAAAEIC@A@AB@BA@ABA@C@CBAB@@AB@DBDBDA@C@A@CAA@CBAB@@@B@BADCAE@E@A@IAC@A@CACACAA@GAKAUFMAMCIGKKMAED@@A@CBC@A@@A@A@A@@AC@@@@CAE@ABBB@B@B@BABB@@@BBDBDB@@@@BB@D@BAB@@@B@B@AC@AAEAC@C@ABCBA@ABACAB@@BD@B@B@BD@DBFDEDEFCNIHE@KCQEEF@PAL@LAFEBGBKFIFIDECMCK@CDAHBHHHPFNDPHDJBPLNNLFLFRBNFLFHEDQBIDILCBEBI@K@O@AAEAKIKEOGMEEAEBED@B@@DBB@B@@BA@@BABB@B@FAB@BB@BADBB@B@BCB@@@@EB@@A@A@@AAA@AA@AA@@@@AAA@AAAAACA@@@A@A@@@@@@A@@A@@@@A@A@@AA@@CA@@A@C@C@AAC@C@GBC@@@@B@@BB@B@@@@@@AB@@@BC@CACCA@ABAB@BA@@@CBAB@@BBBBD@DBBB@@@@@@A@@@C@CAA@@ACAA@ABAB@BABA@@D@@CFAAA@@B@B@D@B@BB@@BLR@BB@BBB@BBBBDFBBFBF@RAF@B@B@BFBDBFBFDD@BNT@@@@@@B@@@@B@@DAF@FBBDBFBDJDB@@B@@BB@@@@B@@BB@@@BBB@@BB@@@@@B@@BD@@@CBAB@B@BABAD@DABAB@BEFC@ADHHFDL@VEF@BDBRAFDHHH@DCF@FDJBF@FDFDBL@FBHAFDDF@FAFEDEFBNBBLBNGFDFJFP@PCDIDKBICCFBJJNNHPBLHTFLHPNRNXPVP^XRTABABABB@BDBBBBBBB@D@B@@@@@BB@@@BB@@BB@@BDD@B@B@BBB@B@BDD@@@@BB@@BB@@@B@@@B@@@@D@D@@B@B@BC@@@A@BD@BAD@BDDBBH@D@B@BB@@@C@A@A@@@A@@@A@@@AA@@@@@DE@CAC@CFIFABCJEJ@TLRHTFNDNBN@FMBKDMFIB@@B@DBBFDDDBB@@B@D@BABCBEBKBIHAHGBGGKIOIMCMAOBGHGLBVLRNLNFJDHAL@FJHR@RGRBNEHCBEAA@GDIBEACCAE@IBCBCBCAAA@A@A@C@ACAAACA@C@CBAB@@@HAB@F@F@D@D@DA@ABGDEDAFAH@JBFBDA@C@CFAD@BAACAACBC@@ABCDABC@ACAIGACC@C@A@KFIFC@C@C@CCAA@EAEAAAA@@@@@A@@B@@@@AB@@@@@BB@@FBD@BADCBA@A@@@A@A@ABAB@@ABABA@@@A@AB@AA@C@@BA@@@@DA@@BA@E@CFAF@FDFFDFLBPNLHTJJAPGJIA@@A@@@ABEBE@A@A@@@ABABABA@@BABADCBAB@BABAB@B@@@B@BAD@B@@DB@@@@BABA@AB@B@@AB@B@BAB@BABABA@CBABA@CBBB@@@BB@@DBBB@BAFCDABA@ADABABCBAB@@@@D@D@BDBD@BAHC@AD@L@LDFFHDJBHADABCBEBO@AAAI@EACC@GD@J@F@FAACCOECC@@AIIAE"],["@@B[@UCQGM@@@@AAIMIKMEOAUBIHGNGH@@ALIRABJ^B\\FNCRFLPAHEJGRKVIRGHA"],["@@@AD@B@@@@A@@D@DAB@@E@BACCAA@@@C@C@CAA@@D@B@BA@"]],"encodeOffsets":[[[108832,26877]],[[108913,26910]],[[108777,26658]]]}},{"type":"Feature","id":"520402002","properties":{"name":"东街街道办事处","childNum":3,"cp":[105.940446,26.249541]},"geometry":{"type":"MultiPolygon","coordinates":[["@@AGECQBUBGA@OOGCKPCVDXAPIDI@@BABABAFCLEFCDEAAEAE@C@CAECCGAGBEA@@@@C@@@A@A@C@AAA@A@A@ABA@A@@@A@CA@@A@AA@@A@A@@@AAA@A@@AA@C@A@C@AA@@A@A@CA@AC@AAA@C@@@A@AAA@@@AA@AA@@A@@BA@@B@@A@AAAAACEAGACACAAC@CBCFAHAPBH@@@B@@@@@@@FABABC@A@@@AB@@A@@@@LMDOEIKGKIIGOFENEFMAGOCYC[AKCSAC@AA@@@A@CKACAAA@C@C@@AACAA@CBA@@B@GI@BCDA@A@A@A@AB@BA@@@A@@CAACI@C@CB@BAD@D@@@AE@A@CBABABA@C@CBADGAAACC@C@A@@@BA@C@AAA@E@@D@D@@@BC@C@EACAAA@AB@BAB@D@@ABA@@@@BA@ACC@A@CACAA@C@A@C@@A@@BA@@AAA@A@A@@A@A@AAE@A@C@G@EAAAAAAC@CBAB@@A@@@@B@BABA@CAABA@@E@IBEAAAAA@@A@ADCB@D@@A@C@ACAAAADAB@B@BCA@@A@A@@ABA@A@A@@C@CCAIECIBCH@L@NANATATCLIPKLOHQFKDQBOCIAGDAFEJCHEHCLGHGJQ@MAIEQGIIKKGKECAACCECAAA@@A@CAAAAEIC@A@AB@BA@ABA@C@CBAB@@AB@DBDBDA@C@A@CAA@CBAB@@@B@BADCAE@E@A@IAC@A@CACACAA@GAKAUFMAMCIGKKMAED@@A@CBC@A@@A@A@A@@AC@@@@CAE@ABBB@B@B@BABB@@@BBDBDB@@@@BB@D@BAB@@@B@B@AC@AAEAC@C@ABCBA@ABACAB@@BD@B@B@BD@DBFDEDEFCNIHE@KCQEEF@PAL@LAFEBGBKFIFIDECMCK@CDAHBHHHPFNDPHDJBPLNNLFLFRBNFLFHEDQBIDILCBEBI@K@O@AAEAKIKEOGMEEAEBED@B@@DBB@B@@BA@@BABB@B@FAB@BB@BADBB@B@BCB@@@@EB@@A@A@@AAA@AA@AA@@@@AAA@AAAAACA@@@A@A@@@@@@A@@A@@@@A@A@@AA@@CA@@A@C@C@AAC@C@GBC@@@@B@@BB@B@@@@@@AB@@@BC@CACCA@ABAB@BA@@@CBAB@@BBBBD@DBBB@@@@@@A@@@C@CAA@@ACAA@ABAB@BABA@@D@@CFAAA@@B@B@D@B@BB@@BLR@BB@BBB@BBBBDFBBFBF@RAF@B@B@BFBDBFBFDD@BNT@@@@@@B@@@@B@@DAF@FBBDBFBDJDB@@B@@BB@@@@B@@BB@@@BBB@@BB@@@@@B@@BD@@@CBAB@B@BABAD@DABAB@BEFC@ADHHFDL@VEF@BDBRAFDHHH@DCF@FDJBF@FDFDBL@FBHAFDDF@FAFEDEFBNBBLBNGFDFJFP@PCDIDKBICCFBJJNNHPBLHTFLHPNRNXPVP^XRTABABABB@BDBBBBBBB@D@B@@@@@BB@@@BB@@BB@@BDD@B@B@BBB@B@BDD@@@@BB@@BB@@@B@@@B@@@@D@D@@B@B@BC@@@A@BD@BAD@BDDBBH@D@B@BB@@@C@A@A@@@A@@@A@@@AA@@@@@DE@CAC@CFIFABCJEJ@TLRHTFNDNBN@FMBKDMFIB@@B@DBBFDDDBB@@B@D@BABCBEBKBIHAHGBGGKIOIMCMAOBGHGLBVLRNLNFJDHAL@FJHR@RGRBNEHCBEAA@GDIBEACCAE@IBCBCBCAAA@A@A@C@ACAAACA@C@CBAB@@@HAB@F@F@D@D@DA@ABGDEDAFAH@JBFBDA@C@CFAD@BAACAACBC@@ABCDABC@ACAIGACC@C@A@KFIFC@C@C@CCAA@EAEAAAA@@@@@A@@B@@@@AB@@@@@BB@@FBD@BADCBA@A@@@A@A@ABAB@@ABABA@@@A@AB@AA@C@@BA@@@@DA@@BA@E@CFAF@FDFFDFLBPNLHTJJAPGJIA@@A@@@ABEBE@A@A@@@ABABABA@@BABADCBAB@BABAB@B@@@B@BAD@B@@DB@@@@BABA@AB@B@@AB@B@BAB@BABABA@CBABA@CBBB@@@BB@@DBBB@BAFCDABA@ADABABCBAB@@@@D@D@BDBD@BAHC@AD@L@LDFFHDJBHADABCBEBO@AAAI@EACC@GD@J@F@FAACCOECC@@AIIAE"],["@@B[@UCQGM@@@@AAIMIKMEOAUBIHGNGH@@ALIRABJ^B\\FNCRFLPAHEJGRKVIRGHA"],["@@@AD@B@@@@A@@D@DAB@@E@BACCAA@@@C@C@CAA@@D@B@BA@"]],"encodeOffsets":[[[108832,26877]],[[108913,26910]],[[108777,26658]]]}},{"type":"Feature","id":"520402003","properties":{"name":"西街街道办事处","childNum":3,"cp":[105.935161,26.245465]},"geometry":{"type":"MultiPolygon","coordinates":[["@@AGECQBUBGA@OOGCKPCVDXAPIDI@@BABABAFCLEFCDEAAEAE@C@CAECCGAGBEA@@@@C@@@A@A@C@AAA@A@A@ABA@A@@@A@CA@@A@AA@@A@A@@@AAA@A@@AA@C@A@C@AA@@A@A@CA@AC@AAA@C@@@A@AAA@@@AA@AA@@A@@BA@@B@@A@AAAAACEAGACACAAC@CBCFAHAPBH@@@B@@@@@@@FABABC@A@@@AB@@A@@@@LMDOEIKGKIIGOFENEFMAGOCYC[AKCSAC@AA@@@A@CKACAAA@C@C@@AACAA@CBA@@B@GI@BCDA@A@A@A@AB@BA@@@A@@CAACI@C@CB@BAD@D@@@AE@A@CBABABA@C@CBADGAAACC@C@A@@@BA@C@AAA@E@@D@D@@@BC@C@EACAAA@AB@BAB@D@@ABA@@@@BA@ACC@A@CACAA@C@A@C@@A@@BA@@AAA@A@A@@A@A@AAE@A@C@G@EAAAAAAC@CBAB@@A@@@@B@BABA@CAABA@@E@IBEAAAAA@@A@ADCB@D@@A@C@ACAAAADAB@B@BCA@@A@A@@ABA@A@A@@C@CCAIECIBCH@L@NANATATCLIPKLOHQFKDQBOCIAGDAFEJCHEHCLGHGJQ@MAIEQGIIKKGKECAACCECAAA@@A@CAAAAEIC@A@AB@BA@ABA@C@CBAB@@AB@DBDBDA@C@A@CAA@CBAB@@@B@BADCAE@E@A@IAC@A@CACACAA@GAKAUFMAMCIGKKMAED@@A@CBC@A@@A@A@A@@AC@@@@CAE@ABBB@B@B@BABB@@@BBDBDB@@@@BB@D@BAB@@@B@B@AC@AAEAC@C@ABCBA@ABACAB@@BD@B@B@BD@DBFDEDEFCNIHE@KCQEEF@PAL@LAFEBGBKFIFIDECMCK@CDAHBHHHPFNDPHDJBPLNNLFLFRBNFLFHEDQBIDILCBEBI@K@O@AAEAKIKEOGMEEAEBED@B@@DBB@B@@BA@@BABB@B@FAB@BB@BADBB@B@BCB@@@@EB@@A@A@@AAA@AA@AA@@@@AAA@AAAAACA@@@A@A@@@@@@A@@A@@@@A@A@@AA@@CA@@A@C@C@AAC@C@GBC@@@@B@@BB@B@@@@@@AB@@@BC@CACCA@ABAB@BA@@@CBAB@@BBBBD@DBBB@@@@@@A@@@C@CAA@@ACAA@ABAB@BABA@@D@@CFAAA@@B@B@D@B@BB@@BLR@BB@BBB@BBBBDFBBFBF@RAF@B@B@BFBDBFBFDD@BNT@@@@@@B@@@@B@@DAF@FBBDBFBDJDB@@B@@BB@@@@B@@BB@@@BBB@@BB@@@@@B@@BD@@@CBAB@B@BABAD@DABAB@BEFC@ADHHFDL@VEF@BDBRAFDHHH@DCF@FDJBF@FDFDBL@FBHAFDDF@FAFEDEFBNBBLBNGFDFJFP@PCDIDKBICCFBJJNNHPBLHTFLHPNRNXPVP^XRTABABABB@BDBBBBBBB@D@B@@@@@BB@@@BB@@BB@@BDD@B@B@BBB@B@BDD@@@@BB@@BB@@@B@@@B@@@@D@D@@B@B@BC@@@A@BD@BAD@BDDBBH@D@B@BB@@@C@A@A@@@A@@@A@@@AA@@@@@DE@CAC@CFIFABCJEJ@TLRHTFNDNBN@FMBKDMFIB@@B@DBBFDDDBB@@B@D@BABCBEBKBIHAHGBGGKIOIMCMAOBGHGLBVLRNLNFJDHAL@FJHR@RGRBNEHCBEAA@GDIBEACCAE@IBCBCBCAAA@A@A@C@ACAAACA@C@CBAB@@@HAB@F@F@D@D@DA@ABGDEDAFAH@JBFBDA@C@CFAD@BAACAACBC@@ABCDABC@ACAIGACC@C@A@KFIFC@C@C@CCAA@EAEAAAA@@@@@A@@B@@@@AB@@@@@BB@@FBD@BADCBA@A@@@A@A@ABAB@@ABABA@@@A@AB@AA@C@@BA@@@@DA@@BA@E@CFAF@FDFFDFLBPNLHTJJAPGJIA@@A@@@ABEBE@A@A@@@ABABABA@@BABADCBAB@BABAB@B@@@B@BAD@B@@DB@@@@BABA@AB@B@@AB@B@BAB@BABABA@CBABA@CBBB@@@BB@@DBBB@BAFCDABA@ADABABCBAB@@@@D@D@BDBD@BAHC@AD@L@LDFFHDJBHADABCBEBO@AAAI@EACC@GD@J@F@FAACCOECC@@AIIAE"],["@@B[@UCQGM@@@@AAIMIKMEOAUBIHGNGH@@ALIRABJ^B\\FNCRFLPAHEJGRKVIRGHA"],["@@@AD@B@@@@A@@D@DAB@@E@BACCAA@@@C@C@CAA@@D@B@BA@"]],"encodeOffsets":[[[108832,26877]],[[108913,26910]],[[108777,26658]]]}},{"type":"Feature","id":"520402004","properties":{"name":"北街街道办事处","childNum":3,"cp":[105.935184,26.256713]},"geometry":{"type":"MultiPolygon","coordinates":[["@@AGECQBUBGA@OOGCKPCVDXAPIDI@@BABABAFCLEFCDEAAEAE@C@CAECCGAGBEA@@@@C@@@A@A@C@AAA@A@A@ABA@A@@@A@CA@@A@AA@@A@A@@@AAA@A@@AA@C@A@C@AA@@A@A@CA@AC@AAA@C@@@A@AAA@@@AA@AA@@A@@BA@@B@@A@AAAAACEAGACACAAC@CBCFAHAPBH@@@B@@@@@@@FABABC@A@@@AB@@A@@@@LMDOEIKGKIIGOFENEFMAGOCYC[AKCSAC@AA@@@A@CKACAAA@C@C@@AACAA@CBA@@B@GI@BCDA@A@A@A@AB@BA@@@A@@CAACI@C@CB@BAD@D@@@AE@A@CBABABA@C@CBADGAAACC@C@A@@@BA@C@AAA@E@@D@D@@@BC@C@EACAAA@AB@BAB@D@@ABA@@@@BA@ACC@A@CACAA@C@A@C@@A@@BA@@AAA@A@A@@A@A@AAE@A@C@G@EAAAAAAC@CBAB@@A@@@@B@BABA@CAABA@@E@IBEAAAAA@@A@ADCB@D@@A@C@ACAAAADAB@B@BCA@@A@A@@ABA@A@A@@C@CCAIECIBCH@L@NANATATCLIPKLOHQFKDQBOCIAGDAFEJCHEHCLGHGJQ@MAIEQGIIKKGKECAACCECAAA@@A@CAAAAEIC@A@AB@BA@ABA@C@CBAB@@AB@DBDBDA@C@A@CAA@CBAB@@@B@BADCAE@E@A@IAC@A@CACACAA@GAKAUFMAMCIGKKMAED@@A@CBC@A@@A@A@A@@AC@@@@CAE@ABBB@B@B@BABB@@@BBDBDB@@@@BB@D@BAB@@@B@B@AC@AAEAC@C@ABCBA@ABACAB@@BD@B@B@BD@DBFDEDEFCNIHE@KCQEEF@PAL@LAFEBGBKFIFIDECMCK@CDAHBHHHPFNDPHDJBPLNNLFLFRBNFLFHEDQBIDILCBEBI@K@O@AAEAKIKEOGMEEAEBED@B@@DBB@B@@BA@@BABB@B@FAB@BB@BADBB@B@BCB@@@@EB@@A@A@@AAA@AA@AA@@@@AAA@AAAAACA@@@A@A@@@@@@A@@A@@@@A@A@@AA@@CA@@A@C@C@AAC@C@GBC@@@@B@@BB@B@@@@@@AB@@@BC@CACCA@ABAB@BA@@@CBAB@@BBBBD@DBBB@@@@@@A@@@C@CAA@@ACAA@ABAB@BABA@@D@@CFAAA@@B@B@D@B@BB@@BLR@BB@BBB@BBBBDFBBFBF@RAF@B@B@BFBDBFBFDD@BNT@@@@@@B@@@@B@@DAF@FBBDBFBDJDB@@B@@BB@@@@B@@BB@@@BBB@@BB@@@@@B@@BD@@@CBAB@B@BABAD@DABAB@BEFC@ADHHFDL@VEF@BDBRAFDHHH@DCF@FDJBF@FDFDBL@FBHAFDDF@FAFEDEFBNBBLBNGFDFJFP@PCDIDKBICCFBJJNNHPBLHTFLHPNRNXPVP^XRTABABABB@BDBBBBBBB@D@B@@@@@BB@@@BB@@BB@@BDD@B@B@BBB@B@BDD@@@@BB@@BB@@@B@@@B@@@@D@D@@B@B@BC@@@A@BD@BAD@BDDBBH@D@B@BB@@@C@A@A@@@A@@@A@@@AA@@@@@DE@CAC@CFIFABCJEJ@TLRHTFNDNBN@FMBKDMFIB@@B@DBBFDDDBB@@B@D@BABCBEBKBIHAHGBGGKIOIMCMAOBGHGLBVLRNLNFJDHAL@FJHR@RGRBNEHCBEAA@GDIBEACCAE@IBCBCBCAAA@A@A@C@ACAAACA@C@CBAB@@@HAB@F@F@D@D@DA@ABGDEDAFAH@JBFBDA@C@CFAD@BAACAACBC@@ABCDABC@ACAIGACC@C@A@KFIFC@C@C@CCAA@EAEAAAA@@@@@A@@B@@@@AB@@@@@BB@@FBD@BADCBA@A@@@A@A@ABAB@@ABABA@@@A@AB@AA@C@@BA@@@@DA@@BA@E@CFAF@FDFFDFLBPNLHTJJAPGJIA@@A@@@ABEBE@A@A@@@ABABABA@@BABADCBAB@BABAB@B@@@B@BAD@B@@DB@@@@BABA@AB@B@@AB@B@BAB@BABABA@CBABA@CBBB@@@BB@@DBBB@BAFCDABA@ADABABCBAB@@@@D@D@BDBD@BAHC@AD@L@LDFFHDJBHADABCBEBO@AAAI@EACC@GD@J@F@FAACCOECC@@AIIAE"],["@@B[@UCQGM@@@@AAIMIKMEOAUBIHGNGH@@ALIRABJ^B\\FNCRFLPAHEJGRKVIRGHA"],["@@@AD@B@@@@A@@D@DAB@@E@BACCAA@@@C@C@CAA@@D@B@BA@"]],"encodeOffsets":[[[108832,26877]],[[108913,26910]],[[108777,26658]]]}},{"type":"Feature","id":"520402005","properties":{"name":"东关街道办事处","childNum":3,"cp":[105.963073,26.260979]},"geometry":{"type":"MultiPolygon","coordinates":[["@@AGECQBUBGA@OOGCKPCVDXAPIDI@@BABABAFCLEFCDEAAEAE@C@CAECCGAGBEA@@@@C@@@A@A@C@AAA@A@A@ABA@A@@@A@CA@@A@AA@@A@A@@@AAA@A@@AA@C@A@C@AA@@A@A@CA@AC@AAA@C@@@A@AAA@@@AA@AA@@A@@BA@@B@@A@AAAAACEAGACACAAC@CBCFAHAPBH@@@B@@@@@@@FABABC@A@@@AB@@A@@@@LMDOEIKGKIIGOFENEFMAGOCYC[AKCSAC@AA@@@A@CKACAAA@C@C@@AACAA@CBA@@B@GI@BCDA@A@A@A@AB@BA@@@A@@CAACI@C@CB@BAD@D@@@AE@A@CBABABA@C@CBADGAAACC@C@A@@@BA@C@AAA@E@@D@D@@@BC@C@EACAAA@AB@BAB@D@@ABA@@@@BA@ACC@A@CACAA@C@A@C@@A@@BA@@AAA@A@A@@A@A@AAE@A@C@G@EAAAAAAC@CBAB@@A@@@@B@BABA@CAABA@@E@IBEAAAAA@@A@ADCB@D@@A@C@ACAAAADAB@B@BCA@@A@A@@ABA@A@A@@C@CCAIECIBCH@L@NANATATCLIPKLOHQFKDQBOCIAGDAFEJCHEHCLGHGJQ@MAIEQGIIKKGKECAACCECAAA@@A@CAAAAEIC@A@AB@BA@ABA@C@CBAB@@AB@DBDBDA@C@A@CAA@CBAB@@@B@BADCAE@E@A@IAC@A@CACACAA@GAKAUFMAMCIGKKMAED@@A@CBC@A@@A@A@A@@AC@@@@CAE@ABBB@B@B@BABB@@@BBDBDB@@@@BB@D@BAB@@@B@B@AC@AAEAC@C@ABCBA@ABACAB@@BD@B@B@BD@DBFDEDEFCNIHE@KCQEEF@PAL@LAFEBGBKFIFIDECMCK@CDAHBHHHPFNDPHDJBPLNNLFLFRBNFLFHEDQBIDILCBEBI@K@O@AAEAKIKEOGMEEAEBED@B@@DBB@B@@BA@@BABB@B@FAB@BB@BADBB@B@BCB@@@@EB@@A@A@@AAA@AA@AA@@@@AAA@AAAAACA@@@A@A@@@@@@A@@A@@@@A@A@@AA@@CA@@A@C@C@AAC@C@GBC@@@@B@@BB@B@@@@@@AB@@@BC@CACCA@ABAB@BA@@@CBAB@@BBBBD@DBBB@@@@@@A@@@C@CAA@@ACAA@ABAB@BABA@@D@@CFAAA@@B@B@D@B@BB@@BLR@BB@BBB@BBBBDFBBFBF@RAF@B@B@BFBDBFBFDD@BNT@@@@@@B@@@@B@@DAF@FBBDBFBDJDB@@B@@BB@@@@B@@BB@@@BBB@@BB@@@@@B@@BD@@@CBAB@B@BABAD@DABAB@BEFC@ADHHFDL@VEF@BDBRAFDHHH@DCF@FDJBF@FDFDBL@FBHAFDDF@FAFEDEFBNBBLBNGFDFJFP@PCDIDKBICCFBJJNNHPBLHTFLHPNRNXPVP^XRTABABABB@BDBBBBBBB@D@B@@@@@BB@@@BB@@BB@@BDD@B@B@BBB@B@BDD@@@@BB@@BB@@@B@@@B@@@@D@D@@B@B@BC@@@A@BD@BAD@BDDBBH@D@B@BB@@@C@A@A@@@A@@@A@@@AA@@@@@DE@CAC@CFIFABCJEJ@TLRHTFNDNBN@FMBKDMFIB@@B@DBBFDDDBB@@B@D@BABCBEBKBIHAHGBGGKIOIMCMAOBGHGLBVLRNLNFJDHAL@FJHR@RGRBNEHCBEAA@GDIBEACCAE@IBCBCBCAAA@A@A@C@ACAAACA@C@CBAB@@@HAB@F@F@D@D@DA@ABGDEDAFAH@JBFBDA@C@CFAD@BAACAACBC@@ABCDABC@ACAIGACC@C@A@KFIFC@C@C@CCAA@EAEAAAA@@@@@A@@B@@@@AB@@@@@BB@@FBD@BADCBA@A@@@A@A@ABAB@@ABABA@@@A@AB@AA@C@@BA@@@@DA@@BA@E@CFAF@FDFFDFLBPNLHTJJAPGJIA@@A@@@ABEBE@A@A@@@ABABABA@@BABADCBAB@BABAB@B@@@B@BAD@B@@DB@@@@BABA@AB@B@@AB@B@BAB@BABABA@CBABA@CBBB@@@BB@@DBBB@BAFCDABA@ADABABCBAB@@@@D@D@BDBD@BAHC@AD@L@LDFFHDJBHADABCBEBO@AAAI@EACC@GD@J@F@FAACCOECC@@AIIAE"],["@@B[@UCQGM@@@@AAIMIKMEOAUBIHGNGH@@ALIRABJ^B\\FNCRFLPAHEJGRKVIRGHA"],["@@@AD@B@@@@A@@D@DAB@@E@BACCAA@@@C@C@CAA@@D@B@BA@"]],"encodeOffsets":[[[108832,26877]],[[108913,26910]],[[108777,26658]]]}},{"type":"Feature","id":"520402006","properties":{"name":"华西街道办事处","childNum":3,"cp":[105.93327,26.246598]},"geometry":{"type":"MultiPolygon","coordinates":[["@@AGECQBUBGA@OOGCKPCVDXAPIDI@@BABABAFCLEFCDEAAEAE@C@CAECCGAGBEA@@@@C@@@A@A@C@AAA@A@A@ABA@A@@@A@CA@@A@AA@@A@A@@@AAA@A@@AA@C@A@C@AA@@A@A@CA@AC@AAA@C@@@A@AAA@@@AA@AA@@A@@BA@@B@@A@AAAAACEAGACACAAC@CBCFAHAPBH@@@B@@@@@@@FABABC@A@@@AB@@A@@@@LMDOEIKGKIIGOFENEFMAGOCYC[AKCSAC@AA@@@A@CKACAAA@C@C@@AACAA@CBA@@B@GI@BCDA@A@A@A@AB@BA@@@A@@CAACI@C@CB@BAD@D@@@AE@A@CBABABA@C@CBADGAAACC@C@A@@@BA@C@AAA@E@@D@D@@@BC@C@EACAAA@AB@BAB@D@@ABA@@@@BA@ACC@A@CACAA@C@A@C@@A@@BA@@AAA@A@A@@A@A@AAE@A@C@G@EAAAAAAC@CBAB@@A@@@@B@BABA@CAABA@@E@IBEAAAAA@@A@ADCB@D@@A@C@ACAAAADAB@B@BCA@@A@A@@ABA@A@A@@C@CCAIECIBCH@L@NANATATCLIPKLOHQFKDQBOCIAGDAFEJCHEHCLGHGJQ@MAIEQGIIKKGKECAACCECAAA@@A@CAAAAEIC@A@AB@BA@ABA@C@CBAB@@AB@DBDBDA@C@A@CAA@CBAB@@@B@BADCAE@E@A@IAC@A@CACACAA@GAKAUFMAMCIGKKMAED@@A@CBC@A@@A@A@A@@AC@@@@CAE@ABBB@B@B@BABB@@@BBDBDB@@@@BB@D@BAB@@@B@B@AC@AAEAC@C@ABCBA@ABACAB@@BD@B@B@BD@DBFDEDEFCNIHE@KCQEEF@PAL@LAFEBGBKFIFIDECMCK@CDAHBHHHPFNDPHDJBPLNNLFLFRBNFLFHEDQBIDILCBEBI@K@O@AAEAKIKEOGMEEAEBED@B@@DBB@B@@BA@@BABB@B@FAB@BB@BADBB@B@BCB@@@@EB@@A@A@@AAA@AA@AA@@@@AAA@AAAAACA@@@A@A@@@@@@A@@A@@@@A@A@@AA@@CA@@A@C@C@AAC@C@GBC@@@@B@@BB@B@@@@@@AB@@@BC@CACCA@ABAB@BA@@@CBAB@@BBBBD@DBBB@@@@@@A@@@C@CAA@@ACAA@ABAB@BABA@@D@@CFAAA@@B@B@D@B@BB@@BLR@BB@BBB@BBBBDFBBFBF@RAF@B@B@BFBDBFBFDD@BNT@@@@@@B@@@@B@@DAF@FBBDBFBDJDB@@B@@BB@@@@B@@BB@@@BBB@@BB@@@@@B@@BD@@@CBAB@B@BABAD@DABAB@BEFC@ADHHFDL@VEF@BDBRAFDHHH@DCF@FDJBF@FDFDBL@FBHAFDDF@FAFEDEFBNBBLBNGFDFJFP@PCDIDKBICCFBJJNNHPBLHTFLHPNRNXPVP^XRTABABABB@BDBBBBBBB@D@B@@@@@BB@@@BB@@BB@@BDD@B@B@BBB@B@BDD@@@@BB@@BB@@@B@@@B@@@@D@D@@B@B@BC@@@A@BD@BAD@BDDBBH@D@B@BB@@@C@A@A@@@A@@@A@@@AA@@@@@DE@CAC@CFIFABCJEJ@TLRHTFNDNBN@FMBKDMFIB@@B@DBBFDDDBB@@B@D@BABCBEBKBIHAHGBGGKIOIMCMAOBGHGLBVLRNLNFJDHAL@FJHR@RGRBNEHCBEAA@GDIBEACCAE@IBCBCBCAAA@A@A@C@ACAAACA@C@CBAB@@@HAB@F@F@D@D@DA@ABGDEDAFAH@JBFBDA@C@CFAD@BAACAACBC@@ABCDABC@ACAIGACC@C@A@KFIFC@C@C@CCAA@EAEAAAA@@@@@A@@B@@@@AB@@@@@BB@@FBD@BADCBA@A@@@A@A@ABAB@@ABABA@@@A@AB@AA@C@@BA@@@@DA@@BA@E@CFAF@FDFFDFLBPNLHTJJAPGJIA@@A@@@ABEBE@A@A@@@ABABABA@@BABADCBAB@BABAB@B@@@B@BAD@B@@DB@@@@BABA@AB@B@@AB@B@BAB@BABABA@CBABA@CBBB@@@BB@@DBBB@BAFCDABA@ADABABCBAB@@@@D@D@BDBD@BAHC@AD@L@LDFFHDJBHADABCBEBO@AAAI@EACC@GD@J@F@FAACCOECC@@AIIAE"],["@@B[@UCQGM@@@@AAIMIKMEOAUBIHGNGH@@ALIRABJ^B\\FNCRFLPAHEJGRKVIRGHA"],["@@@AD@B@@@@A@@D@DAB@@E@BACCAA@@@C@C@CAA@@D@B@BA@"]],"encodeOffsets":[[[108832,26877]],[[108913,26910]],[[108777,26658]]]}},{"type":"Feature","id":"520402007","properties":{"name":"西航街道办事处","childNum":3,"cp":[105.921945,26.257415]},"geometry":{"type":"MultiPolygon","coordinates":[["@@AGECQBUBGA@OOGCKPCVDXAPIDI@@BABABAFCLEFCDEAAEAE@C@CAECCGAGBEA@@@@C@@@A@A@C@AAA@A@A@ABA@A@@@A@CA@@A@AA@@A@A@@@AAA@A@@AA@C@A@C@AA@@A@A@CA@AC@AAA@C@@@A@AAA@@@AA@AA@@A@@BA@@B@@A@AAAAACEAGACACAAC@CBCFAHAPBH@@@B@@@@@@@FABABC@A@@@AB@@A@@@@LMDOEIKGKIIGOFENEFMAGOCYC[AKCSAC@AA@@@A@CKACAAA@C@C@@AACAA@CBA@@B@GI@BCDA@A@A@A@AB@BA@@@A@@CAACI@C@CB@BAD@D@@@AE@A@CBABABA@C@CBADGAAACC@C@A@@@BA@C@AAA@E@@D@D@@@BC@C@EACAAA@AB@BAB@D@@ABA@@@@BA@ACC@A@CACAA@C@A@C@@A@@BA@@AAA@A@A@@A@A@AAE@A@C@G@EAAAAAAC@CBAB@@A@@@@B@BABA@CAABA@@E@IBEAAAAA@@A@ADCB@D@@A@C@ACAAAADAB@B@BCA@@A@A@@ABA@A@A@@C@CCAIECIBCH@L@NANATATCLIPKLOHQFKDQBOCIAGDAFEJCHEHCLGHGJQ@MAIEQGIIKKGKECAACCECAAA@@A@CAAAAEIC@A@AB@BA@ABA@C@CBAB@@AB@DBDBDA@C@A@CAA@CBAB@@@B@BADCAE@E@A@IAC@A@CACACAA@GAKAUFMAMCIGKKMAED@@A@CBC@A@@A@A@A@@AC@@@@CAE@ABBB@B@B@BABB@@@BBDBDB@@@@BB@D@BAB@@@B@B@AC@AAEAC@C@ABCBA@ABACAB@@BD@B@B@BD@DBFDEDEFCNIHE@KCQEEF@PAL@LAFEBGBKFIFIDECMCK@CDAHBHHHPFNDPHDJBPLNNLFLFRBNFLFHEDQBIDILCBEBI@K@O@AAEAKIKEOGMEEAEBED@B@@DBB@B@@BA@@BABB@B@FAB@BB@BADBB@B@BCB@@@@EB@@A@A@@AAA@AA@AA@@@@AAA@AAAAACA@@@A@A@@@@@@A@@A@@@@A@A@@AA@@CA@@A@C@C@AAC@C@GBC@@@@B@@BB@B@@@@@@AB@@@BC@CACCA@ABAB@BA@@@CBAB@@BBBBD@DBBB@@@@@@A@@@C@CAA@@ACAA@ABAB@BABA@@D@@CFAAA@@B@B@D@B@BB@@BLR@BB@BBB@BBBBDFBBFBF@RAF@B@B@BFBDBFBFDD@BNT@@@@@@B@@@@B@@DAF@FBBDBFBDJDB@@B@@BB@@@@B@@BB@@@BBB@@BB@@@@@B@@BD@@@CBAB@B@BABAD@DABAB@BEFC@ADHHFDL@VEF@BDBRAFDHHH@DCF@FDJBF@FDFDBL@FBHAFDDF@FAFEDEFBNBBLBNGFDFJFP@PCDIDKBICCFBJJNNHPBLHTFLHPNRNXPVP^XRTABABABB@BDBBBBBBB@D@B@@@@@BB@@@BB@@BB@@BDD@B@B@BBB@B@BDD@@@@BB@@BB@@@B@@@B@@@@D@D@@B@B@BC@@@A@BD@BAD@BDDBBH@D@B@BB@@@C@A@A@@@A@@@A@@@AA@@@@@DE@CAC@CFIFABCJEJ@TLRHTFNDNBN@FMBKDMFIB@@B@DBBFDDDBB@@B@D@BABCBEBKBIHAHGBGGKIOIMCMAOBGHGLBVLRNLNFJDHAL@FJHR@RGRBNEHCBEAA@GDIBEACCAE@IBCBCBCAAA@A@A@C@ACAAACA@C@CBAB@@@HAB@F@F@D@D@DA@ABGDEDAFAH@JBFBDA@C@CFAD@BAACAACBC@@ABCDABC@ACAIGACC@C@A@KFIFC@C@C@CCAA@EAEAAAA@@@@@A@@B@@@@AB@@@@@BB@@FBD@BADCBA@A@@@A@A@ABAB@@ABABA@@@A@AB@AA@C@@BA@@@@DA@@BA@E@CFAF@FDFFDFLBPNLHTJJAPGJIA@@A@@@ABEBE@A@A@@@ABABABA@@BABADCBAB@BABAB@B@@@B@BAD@B@@DB@@@@BABA@AB@B@@AB@B@BAB@BABABA@CBABA@CBBB@@@BB@@DBBB@BAFCDABA@ADABABCBAB@@@@D@D@BDBD@BAHC@AD@L@LDFFHDJBHADABCBEBO@AAAI@EACC@GD@J@F@FAACCOECC@@AIIAE"],["@@B[@UCQGM@@@@AAIMIKMEOAUBIHGNGH@@ALIRABJ^B\\FNCRFLPAHEJGRKVIRGHA"],["@@@AD@B@@@@A@@D@DAB@@E@BACCAA@@@C@C@CAA@@D@B@BA@"]],"encodeOffsets":[[[108832,26877]],[[108913,26910]],[[108777,26658]]]}},{"type":"Feature","id":"520402100","properties":{"name":"宋旗镇","childNum":3,"cp":[105.877472,26.238775]},"geometry":{"type":"MultiPolygon","coordinates":[["@@AGECQBUBGA@OOGCKPCVDXAPIDI@@BABABAFCLEFCDEAAEAE@C@CAECCGAGBEA@@@@C@@@A@A@C@AAA@A@A@ABA@A@@@A@CA@@A@AA@@A@A@@@AAA@A@@AA@C@A@C@AA@@A@A@CA@AC@AAA@C@@@A@AAA@@@AA@AA@@A@@BA@@B@@A@AAAAACEAGACACAAC@CBCFAHAPBH@@@B@@@@@@@FABABC@A@@@AB@@A@@@@LMDOEIKGKIIGOFENEFMAGOCYC[AKCSAC@AA@@@A@CKACAAA@C@C@@AACAA@CBA@@B@GI@BCDA@A@A@A@AB@BA@@@A@@CAACI@C@CB@BAD@D@@@AE@A@CBABABA@C@CBADGAAACC@C@A@@@BA@C@AAA@E@@D@D@@@BC@C@EACAAA@AB@BAB@D@@ABA@@@@BA@ACC@A@CACAA@C@A@C@@A@@BA@@AAA@A@A@@A@A@AAE@A@C@G@EAAAAAAC@CBAB@@A@@@@B@BABA@CAABA@@E@IBEAAAAA@@A@ADCB@D@@A@C@ACAAAADAB@B@BCA@@A@A@@ABA@A@A@@C@CCAIECIBCH@L@NANATATCLIPKLOHQFKDQBOCIAGDAFEJCHEHCLGHGJQ@MAIEQGIIKKGKECAACCECAAA@@A@CAAAAEIC@A@AB@BA@ABA@C@CBAB@@AB@DBDBDA@C@A@CAA@CBAB@@@B@BADCAE@E@A@IAC@A@CACACAA@GAKAUFMAMCIGKKMAED@@A@CBC@A@@A@A@A@@AC@@@@CAE@ABBB@B@B@BABB@@@BBDBDB@@@@BB@D@BAB@@@B@B@AC@AAEAC@C@ABCBA@ABACAB@@BD@B@B@BD@DBFDEDEFCNIHE@KCQEEF@PAL@LAFEBGBKFIFIDECMCK@CDAHBHHHPFNDPHDJBPLNNLFLFRBNFLFHEDQBIDILCBEBI@K@O@AAEAKIKEOGMEEAEBED@B@@DBB@B@@BA@@BABB@B@FAB@BB@BADBB@B@BCB@@@@EB@@A@A@@AAA@AA@AA@@@@AAA@AAAAACA@@@A@A@@@@@@A@@A@@@@A@A@@AA@@CA@@A@C@C@AAC@C@GBC@@@@B@@BB@B@@@@@@AB@@@BC@CACCA@ABAB@BA@@@CBAB@@BBBBD@DBBB@@@@@@A@@@C@CAA@@ACAA@ABAB@BABA@@D@@CFAAA@@B@B@D@B@BB@@BLR@BB@BBB@BBBBDFBBFBF@RAF@B@B@BFBDBFBFDD@BNT@@@@@@B@@@@B@@DAF@FBBDBFBDJDB@@B@@BB@@@@B@@BB@@@BBB@@BB@@@@@B@@BD@@@CBAB@B@BABAD@DABAB@BEFC@ADHHFDL@VEF@BDBRAFDHHH@DCF@FDJBF@FDFDBL@FBHAFDDF@FAFEDEFBNBBLBNGFDFJFP@PCDIDKBICCFBJJNNHPBLHTFLHPNRNXPVP^XRTABABABB@BDBBBBBBB@D@B@@@@@BB@@@BB@@BB@@BDD@B@B@BBB@B@BDD@@@@BB@@BB@@@B@@@B@@@@D@D@@B@B@BC@@@A@BD@BAD@BDDBBH@D@B@BB@@@C@A@A@@@A@@@A@@@AA@@@@@DE@CAC@CFIFABCJEJ@TLRHTFNDNBN@FMBKDMFIB@@B@DBBFDDDBB@@B@D@BABCBEBKBIHAHGBGGKIOIMCMAOBGHGLBVLRNLNFJDHAL@FJHR@RGRBNEHCBEAA@GDIBEACCAE@IBCBCBCAAA@A@A@C@ACAAACA@C@CBAB@@@HAB@F@F@D@D@DA@ABGDEDAFAH@JBFBDA@C@CFAD@BAACAACBC@@ABCDABC@ACAIGACC@C@A@KFIFC@C@C@CCAA@EAEAAAA@@@@@A@@B@@@@AB@@@@@BB@@FBD@BADCBA@A@@@A@A@ABAB@@ABABA@@@A@AB@AA@C@@BA@@@@DA@@BA@E@CFAF@FDFFDFLBPNLHTJJAPGJIA@@A@@@ABEBE@A@A@@@ABABABA@@BABADCBAB@BABAB@B@@@B@BAD@B@@DB@@@@BABA@AB@B@@AB@B@BAB@BABABA@CBABA@CBBB@@@BB@@DBBB@BAFCDABA@ADABABCBAB@@@@D@D@BDBD@BAHC@AD@L@LDFFHDJBHADABCBEBO@AAAI@EACC@GD@J@F@FAACCOECC@@AIIAE"],["@@B[@UCQGM@@@@AAIMIKMEOAUBIHGNGH@@ALIRABJ^B\\FNCRFLPAHEJGRKVIRGHA"],["@@@AD@B@@@@A@@D@DAB@@E@BACCAA@@@C@C@CAA@@D@B@BA@"]],"encodeOffsets":[[[108832,26877]],[[108913,26910]],[[108777,26658]]]}},{"type":"Feature","id":"520402101","properties":{"name":"幺铺镇","childNum":3,"cp":[105.858543,26.172687]},"geometry":{"type":"MultiPolygon","coordinates":[["@@AGECQBUBGA@OOGCKPCVDXAPIDI@@BABABAFCLEFCDEAAEAE@C@CAECCGAGBEA@@@@C@@@A@A@C@AAA@A@A@ABA@A@@@A@CA@@A@AA@@A@A@@@AAA@A@@AA@C@A@C@AA@@A@A@CA@AC@AAA@C@@@A@AAA@@@AA@AA@@A@@BA@@B@@A@AAAAACEAGACACAAC@CBCFAHAPBH@@@B@@@@@@@FABABC@A@@@AB@@A@@@@LMDOEIKGKIIGOFENEFMAGOCYC[AKCSAC@AA@@@A@CKACAAA@C@C@@AACAA@CBA@@B@GI@BCDA@A@A@A@AB@BA@@@A@@CAACI@C@CB@BAD@D@@@AE@A@CBABABA@C@CBADGAAACC@C@A@@@BA@C@AAA@E@@D@D@@@BC@C@EACAAA@AB@BAB@D@@ABA@@@@BA@ACC@A@CACAA@C@A@C@@A@@BA@@AAA@A@A@@A@A@AAE@A@C@G@EAAAAAAC@CBAB@@A@@@@B@BABA@CAABA@@E@IBEAAAAA@@A@ADCB@D@@A@C@ACAAAADAB@B@BCA@@A@A@@ABA@A@A@@C@CCAIECIBCH@L@NANATATCLIPKLOHQFKDQBOCIAGDAFEJCHEHCLGHGJQ@MAIEQGIIKKGKECAACCECAAA@@A@CAAAAEIC@A@AB@BA@ABA@C@CBAB@@AB@DBDBDA@C@A@CAA@CBAB@@@B@BADCAE@E@A@IAC@A@CACACAA@GAKAUFMAMCIGKKMAED@@A@CBC@A@@A@A@A@@AC@@@@CAE@ABBB@B@B@BABB@@@BBDBDB@@@@BB@D@BAB@@@B@B@AC@AAEAC@C@ABCBA@ABACAB@@BD@B@B@BD@DBFDEDEFCNIHE@KCQEEF@PAL@LAFEBGBKFIFIDECMCK@CDAHBHHHPFNDPHDJBPLNNLFLFRBNFLFHEDQBIDILCBEBI@K@O@AAEAKIKEOGMEEAEBED@B@@DBB@B@@BA@@BABB@B@FAB@BB@BADBB@B@BCB@@@@EB@@A@A@@AAA@AA@AA@@@@AAA@AAAAACA@@@A@A@@@@@@A@@A@@@@A@A@@AA@@CA@@A@C@C@AAC@C@GBC@@@@B@@BB@B@@@@@@AB@@@BC@CACCA@ABAB@BA@@@CBAB@@BBBBD@DBBB@@@@@@A@@@C@CAA@@ACAA@ABAB@BABA@@D@@CFAAA@@B@B@D@B@BB@@BLR@BB@BBB@BBBBDFBBFBF@RAF@B@B@BFBDBFBFDD@BNT@@@@@@B@@@@B@@DAF@FBBDBFBDJDB@@B@@BB@@@@B@@BB@@@BBB@@BB@@@@@B@@BD@@@CBAB@B@BABAD@DABAB@BEFC@ADHHFDL@VEF@BDBRAFDHHH@DCF@FDJBF@FDFDBL@FBHAFDDF@FAFEDEFBNBBLBNGFDFJFP@PCDIDKBICCFBJJNNHPBLHTFLHPNRNXPVP^XRTABABABB@BDBBBBBBB@D@B@@@@@BB@@@BB@@BB@@BDD@B@B@BBB@B@BDD@@@@BB@@BB@@@B@@@B@@@@D@D@@B@B@BC@@@A@BD@BAD@BDDBBH@D@B@BB@@@C@A@A@@@A@@@A@@@AA@@@@@DE@CAC@CFIFABCJEJ@TLRHTFNDNBN@FMBKDMFIB@@B@DBBFDDDBB@@B@D@BABCBEBKBIHAHGBGGKIOIMCMAOBGHGLBVLRNLNFJDHAL@FJHR@RGRBNEHCBEAA@GDIBEACCAE@IBCBCBCAAA@A@A@C@ACAAACA@C@CBAB@@@HAB@F@F@D@D@DA@ABGDEDAFAH@JBFBDA@C@CFAD@BAACAACBC@@ABCDABC@ACAIGACC@C@A@KFIFC@C@C@CCAA@EAEAAAA@@@@@A@@B@@@@AB@@@@@BB@@FBD@BADCBA@A@@@A@A@ABAB@@ABABA@@@A@AB@AA@C@@BA@@@@DA@@BA@E@CFAF@FDFFDFLBPNLHTJJAPGJIA@@A@@@ABEBE@A@A@@@ABABABA@@BABADCBAB@BABAB@B@@@B@BAD@B@@DB@@@@BABA@AB@B@@AB@B@BAB@BABABA@CBABA@CBBB@@@BB@@DBBB@BAFCDABA@ADABABCBAB@@@@D@D@BDBD@BAHC@AD@L@LDFFHDJBHADABCBEBO@AAAI@EACC@GD@J@F@FAACCOECC@@AIIAE"],["@@B[@UCQGM@@@@AAIMIKMEOAUBIHGNGH@@ALIRABJ^B\\FNCRFLPAHEJGRKVIRGHA"],["@@@AD@B@@@@A@@D@DAB@@E@BACCAA@@@C@C@CAA@@D@B@BA@"]],"encodeOffsets":[[[108832,26877]],[[108913,26910]],[[108777,26658]]]}},{"type":"Feature","id":"520402102","properties":{"name":"宁谷镇","childNum":3,"cp":[105.986597,26.211723]},"geometry":{"type":"MultiPolygon","coordinates":[["@@AGECQBUBGA@OOGCKPCVDXAPIDI@@BABABAFCLEFCDEAAEAE@C@CAECCGAGBEA@@@@C@@@A@A@C@AAA@A@A@ABA@A@@@A@CA@@A@AA@@A@A@@@AAA@A@@AA@C@A@C@AA@@A@A@CA@AC@AAA@C@@@A@AAA@@@AA@AA@@A@@BA@@B@@A@AAAAACEAGACACAAC@CBCFAHAPBH@@@B@@@@@@@FABABC@A@@@AB@@A@@@@LMDOEIKGKIIGOFENEFMAGOCYC[AKCSAC@AA@@@A@CKACAAA@C@C@@AACAA@CBA@@B@GI@BCDA@A@A@A@AB@BA@@@A@@CAACI@C@CB@BAD@D@@@AE@A@CBABABA@C@CBADGAAACC@C@A@@@BA@C@AAA@E@@D@D@@@BC@C@EACAAA@AB@BAB@D@@ABA@@@@BA@ACC@A@CACAA@C@A@C@@A@@BA@@AAA@A@A@@A@A@AAE@A@C@G@EAAAAAAC@CBAB@@A@@@@B@BABA@CAABA@@E@IBEAAAAA@@A@ADCB@D@@A@C@ACAAAADAB@B@BCA@@A@A@@ABA@A@A@@C@CCAIECIBCH@L@NANATATCLIPKLOHQFKDQBOCIAGDAFEJCHEHCLGHGJQ@MAIEQGIIKKGKECAACCECAAA@@A@CAAAAEIC@A@AB@BA@ABA@C@CBAB@@AB@DBDBDA@C@A@CAA@CBAB@@@B@BADCAE@E@A@IAC@A@CACACAA@GAKAUFMAMCIGKKMAED@@A@CBC@A@@A@A@A@@AC@@@@CAE@ABBB@B@B@BABB@@@BBDBDB@@@@BB@D@BAB@@@B@B@AC@AAEAC@C@ABCBA@ABACAB@@BD@B@B@BD@DBFDEDEFCNIHE@KCQEEF@PAL@LAFEBGBKFIFIDECMCK@CDAHBHHHPFNDPHDJBPLNNLFLFRBNFLFHEDQBIDILCBEBI@K@O@AAEAKIKEOGMEEAEBED@B@@DBB@B@@BA@@BABB@B@FAB@BB@BADBB@B@BCB@@@@EB@@A@A@@AAA@AA@AA@@@@AAA@AAAAACA@@@A@A@@@@@@A@@A@@@@A@A@@AA@@CA@@A@C@C@AAC@C@GBC@@@@B@@BB@B@@@@@@AB@@@BC@CACCA@ABAB@BA@@@CBAB@@BBBBD@DBBB@@@@@@A@@@C@CAA@@ACAA@ABAB@BABA@@D@@CFAAA@@B@B@D@B@BB@@BLR@BB@BBB@BBBBDFBBFBF@RAF@B@B@BFBDBFBFDD@BNT@@@@@@B@@@@B@@DAF@FBBDBFBDJDB@@B@@BB@@@@B@@BB@@@BBB@@BB@@@@@B@@BD@@@CBAB@B@BABAD@DABAB@BEFC@ADHHFDL@VEF@BDBRAFDHHH@DCF@FDJBF@FDFDBL@FBHAFDDF@FAFEDEFBNBBLBNGFDFJFP@PCDIDKBICCFBJJNNHPBLHTFLHPNRNXPVP^XRTABABABB@BDBBBBBBB@D@B@@@@@BB@@@BB@@BB@@BDD@B@B@BBB@B@BDD@@@@BB@@BB@@@B@@@B@@@@D@D@@B@B@BC@@@A@BD@BAD@BDDBBH@D@B@BB@@@C@A@A@@@A@@@A@@@AA@@@@@DE@CAC@CFIFABCJEJ@TLRHTFNDNBN@FMBKDMFIB@@B@DBBFDDDBB@@B@D@BABCBEBKBIHAHGBGGKIOIMCMAOBGHGLBVLRNLNFJDHAL@FJHR@RGRBNEHCBEAA@GDIBEACCAE@IBCBCBCAAA@A@A@C@ACAAACA@C@CBAB@@@HAB@F@F@D@D@DA@ABGDEDAFAH@JBFBDA@C@CFAD@BAACAACBC@@ABCDABC@ACAIGACC@C@A@KFIFC@C@C@CCAA@EAEAAAA@@@@@A@@B@@@@AB@@@@@BB@@FBD@BADCBA@A@@@A@A@ABAB@@ABABA@@@A@AB@AA@C@@BA@@@@DA@@BA@E@CFAF@FDFFDFLBPNLHTJJAPGJIA@@A@@@ABEBE@A@A@@@ABABABA@@BABADCBAB@BABAB@B@@@B@BAD@B@@DB@@@@BABA@AB@B@@AB@B@BAB@BABABA@CBABA@CBBB@@@BB@@DBBB@BAFCDABA@ADABABCBAB@@@@D@D@BDBD@BAHC@AD@L@LDFFHDJBHADABCBEBO@AAAI@EACC@GD@J@F@FAACCOECC@@AIIAE"],["@@B[@UCQGM@@@@AAIMIKMEOAUBIHGNGH@@ALIRABJ^B\\FNCRFLPAHEJGRKVIRGHA"],["@@@AD@B@@@@A@@D@DAB@@E@BACCAA@@@C@C@CAA@@D@B@BA@"]],"encodeOffsets":[[[108832,26877]],[[108913,26910]],[[108777,26658]]]}},{"type":"Feature","id":"520402103","properties":{"name":"龙宫镇","childNum":3,"cp":[105.896779,26.103484]},"geometry":{"type":"MultiPolygon","coordinates":[["@@AGECQBUBGA@OOGCKPCVDXAPIDI@@BABABAFCLEFCDEAAEAE@C@CAECCGAGBEA@@@@C@@@A@A@C@AAA@A@A@ABA@A@@@A@CA@@A@AA@@A@A@@@AAA@A@@AA@C@A@C@AA@@A@A@CA@AC@AAA@C@@@A@AAA@@@AA@AA@@A@@BA@@B@@A@AAAAACEAGACACAAC@CBCFAHAPBH@@@B@@@@@@@FABABC@A@@@AB@@A@@@@LMDOEIKGKIIGOFENEFMAGOCYC[AKCSAC@AA@@@A@CKACAAA@C@C@@AACAA@CBA@@B@GI@BCDA@A@A@A@AB@BA@@@A@@CAACI@C@CB@BAD@D@@@AE@A@CBABABA@C@CBADGAAACC@C@A@@@BA@C@AAA@E@@D@D@@@BC@C@EACAAA@AB@BAB@D@@ABA@@@@BA@ACC@A@CACAA@C@A@C@@A@@BA@@AAA@A@A@@A@A@AAE@A@C@G@EAAAAAAC@CBAB@@A@@@@B@BABA@CAABA@@E@IBEAAAAA@@A@ADCB@D@@A@C@ACAAAADAB@B@BCA@@A@A@@ABA@A@A@@C@CCAIECIBCH@L@NANATATCLIPKLOHQFKDQBOCIAGDAFEJCHEHCLGHGJQ@MAIEQGIIKKGKECAACCECAAA@@A@CAAAAEIC@A@AB@BA@ABA@C@CBAB@@AB@DBDBDA@C@A@CAA@CBAB@@@B@BADCAE@E@A@IAC@A@CACACAA@GAKAUFMAMCIGKKMAED@@A@CBC@A@@A@A@A@@AC@@@@CAE@ABBB@B@B@BABB@@@BBDBDB@@@@BB@D@BAB@@@B@B@AC@AAEAC@C@ABCBA@ABACAB@@BD@B@B@BD@DBFDEDEFCNIHE@KCQEEF@PAL@LAFEBGBKFIFIDECMCK@CDAHBHHHPFNDPHDJBPLNNLFLFRBNFLFHEDQBIDILCBEBI@K@O@AAEAKIKEOGMEEAEBED@B@@DBB@B@@BA@@BABB@B@FAB@BB@BADBB@B@BCB@@@@EB@@A@A@@AAA@AA@AA@@@@AAA@AAAAACA@@@A@A@@@@@@A@@A@@@@A@A@@AA@@CA@@A@C@C@AAC@C@GBC@@@@B@@BB@B@@@@@@AB@@@BC@CACCA@ABAB@BA@@@CBAB@@BBBBD@DBBB@@@@@@A@@@C@CAA@@ACAA@ABAB@BABA@@D@@CFAAA@@B@B@D@B@BB@@BLR@BB@BBB@BBBBDFBBFBF@RAF@B@B@BFBDBFBFDD@BNT@@@@@@B@@@@B@@DAF@FBBDBFBDJDB@@B@@BB@@@@B@@BB@@@BBB@@BB@@@@@B@@BD@@@CBAB@B@BABAD@DABAB@BEFC@ADHHFDL@VEF@BDBRAFDHHH@DCF@FDJBF@FDFDBL@FBHAFDDF@FAFEDEFBNBBLBNGFDFJFP@PCDIDKBICCFBJJNNHPBLHTFLHPNRNXPVP^XRTABABABB@BDBBBBBBB@D@B@@@@@BB@@@BB@@BB@@BDD@B@B@BBB@B@BDD@@@@BB@@BB@@@B@@@B@@@@D@D@@B@B@BC@@@A@BD@BAD@BDDBBH@D@B@BB@@@C@A@A@@@A@@@A@@@AA@@@@@DE@CAC@CFIFABCJEJ@TLRHTFNDNBN@FMBKDMFIB@@B@DBBFDDDBB@@B@D@BABCBEBKBIHAHGBGGKIOIMCMAOBGHGLBVLRNLNFJDHAL@FJHR@RGRBNEHCBEAA@GDIBEACCAE@IBCBCBCAAA@A@A@C@ACAAACA@C@CBAB@@@HAB@F@F@D@D@DA@ABGDEDAFAH@JBFBDA@C@CFAD@BAACAACBC@@ABCDABC@ACAIGACC@C@A@KFIFC@C@C@CCAA@EAEAAAA@@@@@A@@B@@@@AB@@@@@BB@@FBD@BADCBA@A@@@A@A@ABAB@@ABABA@@@A@AB@AA@C@@BA@@@@DA@@BA@E@CFAF@FDFFDFLBPNLHTJJAPGJIA@@A@@@ABEBE@A@A@@@ABABABA@@BABADCBAB@BABAB@B@@@B@BAD@B@@DB@@@@BABA@AB@B@@AB@B@BAB@BABABA@CBABA@CBBB@@@BB@@DBBB@BAFCDABA@ADABABCBAB@@@@D@D@BDBD@BAHC@AD@L@LDFFHDJBHADABCBEBO@AAAI@EACC@GD@J@F@FAACCOECC@@AIIAE"],["@@B[@UCQGM@@@@AAIMIKMEOAUBIHGNGH@@ALIRABJ^B\\FNCRFLPAHEJGRKVIRGHA"],["@@@AD@B@@@@A@@D@DAB@@E@BACCAA@@@C@C@CAA@@D@B@BA@"]],"encodeOffsets":[[[108832,26877]],[[108913,26910]],[[108777,26658]]]}},{"type":"Feature","id":"520402104","properties":{"name":"双堡镇","childNum":3,"cp":[106.190397,26.175245]},"geometry":{"type":"MultiPolygon","coordinates":[["@@AGECQBUBGA@OOGCKPCVDXAPIDI@@BABABAFCLEFCDEAAEAE@C@CAECCGAGBEA@@@@C@@@A@A@C@AAA@A@A@ABA@A@@@A@CA@@A@AA@@A@A@@@AAA@A@@AA@C@A@C@AA@@A@A@CA@AC@AAA@C@@@A@AAA@@@AA@AA@@A@@BA@@B@@A@AAAAACEAGACACAAC@CBCFAHAPBH@@@B@@@@@@@FABABC@A@@@AB@@A@@@@LMDOEIKGKIIGOFENEFMAGOCYC[AKCSAC@AA@@@A@CKACAAA@C@C@@AACAA@CBA@@B@GI@BCDA@A@A@A@AB@BA@@@A@@CAACI@C@CB@BAD@D@@@AE@A@CBABABA@C@CBADGAAACC@C@A@@@BA@C@AAA@E@@D@D@@@BC@C@EACAAA@AB@BAB@D@@ABA@@@@BA@ACC@A@CACAA@C@A@C@@A@@BA@@AAA@A@A@@A@A@AAE@A@C@G@EAAAAAAC@CBAB@@A@@@@B@BABA@CAABA@@E@IBEAAAAA@@A@ADCB@D@@A@C@ACAAAADAB@B@BCA@@A@A@@ABA@A@A@@C@CCAIECIBCH@L@NANATATCLIPKLOHQFKDQBOCIAGDAFEJCHEHCLGHGJQ@MAIEQGIIKKGKECAACCECAAA@@A@CAAAAEIC@A@AB@BA@ABA@C@CBAB@@AB@DBDBDA@C@A@CAA@CBAB@@@B@BADCAE@E@A@IAC@A@CACACAA@GAKAUFMAMCIGKKMAED@@A@CBC@A@@A@A@A@@AC@@@@CAE@ABBB@B@B@BABB@@@BBDBDB@@@@BB@D@BAB@@@B@B@AC@AAEAC@C@ABCBA@ABACAB@@BD@B@B@BD@DBFDEDEFCNIHE@KCQEEF@PAL@LAFEBGBKFIFIDECMCK@CDAHBHHHPFNDPHDJBPLNNLFLFRBNFLFHEDQBIDILCBEBI@K@O@AAEAKIKEOGMEEAEBED@B@@DBB@B@@BA@@BABB@B@FAB@BB@BADBB@B@BCB@@@@EB@@A@A@@AAA@AA@AA@@@@AAA@AAAAACA@@@A@A@@@@@@A@@A@@@@A@A@@AA@@CA@@A@C@C@AAC@C@GBC@@@@B@@BB@B@@@@@@AB@@@BC@CACCA@ABAB@BA@@@CBAB@@BBBBD@DBBB@@@@@@A@@@C@CAA@@ACAA@ABAB@BABA@@D@@CFAAA@@B@B@D@B@BB@@BLR@BB@BBB@BBBBDFBBFBF@RAF@B@B@BFBDBFBFDD@BNT@@@@@@B@@@@B@@DAF@FBBDBFBDJDB@@B@@BB@@@@B@@BB@@@BBB@@BB@@@@@B@@BD@@@CBAB@B@BABAD@DABAB@BEFC@ADHHFDL@VEF@BDBRAFDHHH@DCF@FDJBF@FDFDBL@FBHAFDDF@FAFEDEFBNBBLBNGFDFJFP@PCDIDKBICCFBJJNNHPBLHTFLHPNRNXPVP^XRTABABABB@BDBBBBBBB@D@B@@@@@BB@@@BB@@BB@@BDD@B@B@BBB@B@BDD@@@@BB@@BB@@@B@@@B@@@@D@D@@B@B@BC@@@A@BD@BAD@BDDBBH@D@B@BB@@@C@A@A@@@A@@@A@@@AA@@@@@DE@CAC@CFIFABCJEJ@TLRHTFNDNBN@FMBKDMFIB@@B@DBBFDDDBB@@B@D@BABCBEBKBIHAHGBGGKIOIMCMAOBGHGLBVLRNLNFJDHAL@FJHR@RGRBNEHCBEAA@GDIBEACCAE@IBCBCBCAAA@A@A@C@ACAAACA@C@CBAB@@@HAB@F@F@D@D@DA@ABGDEDAFAH@JBFBDA@C@CFAD@BAACAACBC@@ABCDABC@ACAIGACC@C@A@KFIFC@C@C@CCAA@EAEAAAA@@@@@A@@B@@@@AB@@@@@BB@@FBD@BADCBA@A@@@A@A@ABAB@@ABABA@@@A@AB@AA@C@@BA@@@@DA@@BA@E@CFAF@FDFFDFLBPNLHTJJAPGJIA@@A@@@ABEBE@A@A@@@ABABABA@@BABADCBAB@BABAB@B@@@B@BAD@B@@DB@@@@BABA@AB@B@@AB@B@BAB@BABABA@CBABA@CBBB@@@BB@@DBBB@BAFCDABA@ADABABCBAB@@@@D@D@BDBD@BAHC@AD@L@LDFFHDJBHADABCBEBO@AAAI@EACC@GD@J@F@FAACCOECC@@AIIAE"],["@@B[@UCQGM@@@@AAIMIKMEOAUBIHGNGH@@ALIRABJ^B\\FNCRFLPAHEJGRKVIRGHA"],["@@@AD@B@@@@A@@D@DAB@@E@BACCAA@@@C@C@CAA@@D@B@BA@"]],"encodeOffsets":[[[108832,26877]],[[108913,26910]],[[108777,26658]]]}},{"type":"Feature","id":"520402105","properties":{"name":"大西桥镇","childNum":3,"cp":[106.141046,26.341577]},"geometry":{"type":"MultiPolygon","coordinates":[["@@AGECQBUBGA@OOGCKPCVDXAPIDI@@BABABAFCLEFCDEAAEAE@C@CAECCGAGBEA@@@@C@@@A@A@C@AAA@A@A@ABA@A@@@A@CA@@A@AA@@A@A@@@AAA@A@@AA@C@A@C@AA@@A@A@CA@AC@AAA@C@@@A@AAA@@@AA@AA@@A@@BA@@B@@A@AAAAACEAGACACAAC@CBCFAHAPBH@@@B@@@@@@@FABABC@A@@@AB@@A@@@@LMDOEIKGKIIGOFENEFMAGOCYC[AKCSAC@AA@@@A@CKACAAA@C@C@@AACAA@CBA@@B@GI@BCDA@A@A@A@AB@BA@@@A@@CAACI@C@CB@BAD@D@@@AE@A@CBABABA@C@CBADGAAACC@C@A@@@BA@C@AAA@E@@D@D@@@BC@C@EACAAA@AB@BAB@D@@ABA@@@@BA@ACC@A@CACAA@C@A@C@@A@@BA@@AAA@A@A@@A@A@AAE@A@C@G@EAAAAAAC@CBAB@@A@@@@B@BABA@CAABA@@E@IBEAAAAA@@A@ADCB@D@@A@C@ACAAAADAB@B@BCA@@A@A@@ABA@A@A@@C@CCAIECIBCH@L@NANATATCLIPKLOHQFKDQBOCIAGDAFEJCHEHCLGHGJQ@MAIEQGIIKKGKECAACCECAAA@@A@CAAAAEIC@A@AB@BA@ABA@C@CBAB@@AB@DBDBDA@C@A@CAA@CBAB@@@B@BADCAE@E@A@IAC@A@CACACAA@GAKAUFMAMCIGKKMAED@@A@CBC@A@@A@A@A@@AC@@@@CAE@ABBB@B@B@BABB@@@BBDBDB@@@@BB@D@BAB@@@B@B@AC@AAEAC@C@ABCBA@ABACAB@@BD@B@B@BD@DBFDEDEFCNIHE@KCQEEF@PAL@LAFEBGBKFIFIDECMCK@CDAHBHHHPFNDPHDJBPLNNLFLFRBNFLFHEDQBIDILCBEBI@K@O@AAEAKIKEOGMEEAEBED@B@@DBB@B@@BA@@BABB@B@FAB@BB@BADBB@B@BCB@@@@EB@@A@A@@AAA@AA@AA@@@@AAA@AAAAACA@@@A@A@@@@@@A@@A@@@@A@A@@AA@@CA@@A@C@C@AAC@C@GBC@@@@B@@BB@B@@@@@@AB@@@BC@CACCA@ABAB@BA@@@CBAB@@BBBBD@DBBB@@@@@@A@@@C@CAA@@ACAA@ABAB@BABA@@D@@CFAAA@@B@B@D@B@BB@@BLR@BB@BBB@BBBBDFBBFBF@RAF@B@B@BFBDBFBFDD@BNT@@@@@@B@@@@B@@DAF@FBBDBFBDJDB@@B@@BB@@@@B@@BB@@@BBB@@BB@@@@@B@@BD@@@CBAB@B@BABAD@DABAB@BEFC@ADHHFDL@VEF@BDBRAFDHHH@DCF@FDJBF@FDFDBL@FBHAFDDF@FAFEDEFBNBBLBNGFDFJFP@PCDIDKBICCFBJJNNHPBLHTFLHPNRNXPVP^XRTABABABB@BDBBBBBBB@D@B@@@@@BB@@@BB@@BB@@BDD@B@B@BBB@B@BDD@@@@BB@@BB@@@B@@@B@@@@D@D@@B@B@BC@@@A@BD@BAD@BDDBBH@D@B@BB@@@C@A@A@@@A@@@A@@@AA@@@@@DE@CAC@CFIFABCJEJ@TLRHTFNDNBN@FMBKDMFIB@@B@DBBFDDDBB@@B@D@BABCBEBKBIHAHGBGGKIOIMCMAOBGHGLBVLRNLNFJDHAL@FJHR@RGRBNEHCBEAA@GDIBEACCAE@IBCBCBCAAA@A@A@C@ACAAACA@C@CBAB@@@HAB@F@F@D@D@DA@ABGDEDAFAH@JBFBDA@C@CFAD@BAACAACBC@@ABCDABC@ACAIGACC@C@A@KFIFC@C@C@CCAA@EAEAAAA@@@@@A@@B@@@@AB@@@@@BB@@FBD@BADCBA@A@@@A@A@ABAB@@ABABA@@@A@AB@AA@C@@BA@@@@DA@@BA@E@CFAF@FDFFDFLBPNLHTJJAPGJIA@@A@@@ABEBE@A@A@@@ABABABA@@BABADCBAB@BABAB@B@@@B@BAD@B@@DB@@@@BABA@AB@B@@AB@B@BAB@BABABA@CBABA@CBBB@@@BB@@DBBB@BAFCDABA@ADABABCBAB@@@@D@D@BDBD@BAHC@AD@L@LDFFHDJBHADABCBEBO@AAAI@EACC@GD@J@F@FAACCOECC@@AIIAE"],["@@B[@UCQGM@@@@AAIMIKMEOAUBIHGNGH@@ALIRABJ^B\\FNCRFLPAHEJGRKVIRGHA"],["@@@AD@B@@@@A@@D@DAB@@E@BACCAA@@@C@C@CAA@@D@B@BA@"]],"encodeOffsets":[[[108832,26877]],[[108913,26910]],[[108777,26658]]]}},{"type":"Feature","id":"520402106","properties":{"name":"七眼桥镇","childNum":3,"cp":[106.070606,26.302288]},"geometry":{"type":"MultiPolygon","coordinates":[["@@AGECQBUBGA@OOGCKPCVDXAPIDI@@BABABAFCLEFCDEAAEAE@C@CAECCGAGBEA@@@@C@@@A@A@C@AAA@A@A@ABA@A@@@A@CA@@A@AA@@A@A@@@AAA@A@@AA@C@A@C@AA@@A@A@CA@AC@AAA@C@@@A@AAA@@@AA@AA@@A@@BA@@B@@A@AAAAACEAGACACAAC@CBCFAHAPBH@@@B@@@@@@@FABABC@A@@@AB@@A@@@@LMDOEIKGKIIGOFENEFMAGOCYC[AKCSAC@AA@@@A@CKACAAA@C@C@@AACAA@CBA@@B@GI@BCDA@A@A@A@AB@BA@@@A@@CAACI@C@CB@BAD@D@@@AE@A@CBABABA@C@CBADGAAACC@C@A@@@BA@C@AAA@E@@D@D@@@BC@C@EACAAA@AB@BAB@D@@ABA@@@@BA@ACC@A@CACAA@C@A@C@@A@@BA@@AAA@A@A@@A@A@AAE@A@C@G@EAAAAAAC@CBAB@@A@@@@B@BABA@CAABA@@E@IBEAAAAA@@A@ADCB@D@@A@C@ACAAAADAB@B@BCA@@A@A@@ABA@A@A@@C@CCAIECIBCH@L@NANATATCLIPKLOHQFKDQBOCIAGDAFEJCHEHCLGHGJQ@MAIEQGIIKKGKECAACCECAAA@@A@CAAAAEIC@A@AB@BA@ABA@C@CBAB@@AB@DBDBDA@C@A@CAA@CBAB@@@B@BADCAE@E@A@IAC@A@CACACAA@GAKAUFMAMCIGKKMAED@@A@CBC@A@@A@A@A@@AC@@@@CAE@ABBB@B@B@BABB@@@BBDBDB@@@@BB@D@BAB@@@B@B@AC@AAEAC@C@ABCBA@ABACAB@@BD@B@B@BD@DBFDEDEFCNIHE@KCQEEF@PAL@LAFEBGBKFIFIDECMCK@CDAHBHHHPFNDPHDJBPLNNLFLFRBNFLFHEDQBIDILCBEBI@K@O@AAEAKIKEOGMEEAEBED@B@@DBB@B@@BA@@BABB@B@FAB@BB@BADBB@B@BCB@@@@EB@@A@A@@AAA@AA@AA@@@@AAA@AAAAACA@@@A@A@@@@@@A@@A@@@@A@A@@AA@@CA@@A@C@C@AAC@C@GBC@@@@B@@BB@B@@@@@@AB@@@BC@CACCA@ABAB@BA@@@CBAB@@BBBBD@DBBB@@@@@@A@@@C@CAA@@ACAA@ABAB@BABA@@D@@CFAAA@@B@B@D@B@BB@@BLR@BB@BBB@BBBBDFBBFBF@RAF@B@B@BFBDBFBFDD@BNT@@@@@@B@@@@B@@DAF@FBBDBFBDJDB@@B@@BB@@@@B@@BB@@@BBB@@BB@@@@@B@@BD@@@CBAB@B@BABAD@DABAB@BEFC@ADHHFDL@VEF@BDBRAFDHHH@DCF@FDJBF@FDFDBL@FBHAFDDF@FAFEDEFBNBBLBNGFDFJFP@PCDIDKBICCFBJJNNHPBLHTFLHPNRNXPVP^XRTABABABB@BDBBBBBBB@D@B@@@@@BB@@@BB@@BB@@BDD@B@B@BBB@B@BDD@@@@BB@@BB@@@B@@@B@@@@D@D@@B@B@BC@@@A@BD@BAD@BDDBBH@D@B@BB@@@C@A@A@@@A@@@A@@@AA@@@@@DE@CAC@CFIFABCJEJ@TLRHTFNDNBN@FMBKDMFIB@@B@DBBFDDDBB@@B@D@BABCBEBKBIHAHGBGGKIOIMCMAOBGHGLBVLRNLNFJDHAL@FJHR@RGRBNEHCBEAA@GDIBEACCAE@IBCBCBCAAA@A@A@C@ACAAACA@C@CBAB@@@HAB@F@F@D@D@DA@ABGDEDAFAH@JBFBDA@C@CFAD@BAACAACBC@@ABCDABC@ACAIGACC@C@A@KFIFC@C@C@CCAA@EAEAAAA@@@@@A@@B@@@@AB@@@@@BB@@FBD@BADCBA@A@@@A@A@ABAB@@ABABA@@@A@AB@AA@C@@BA@@@@DA@@BA@E@CFAF@FDFFDFLBPNLHTJJAPGJIA@@A@@@ABEBE@A@A@@@ABABABA@@BABADCBAB@BABAB@B@@@B@BAD@B@@DB@@@@BABA@AB@B@@AB@B@BAB@BABABA@CBABA@CBBB@@@BB@@DBBB@BAFCDABA@ADABABCBAB@@@@D@D@BDBD@BAHC@AD@L@LDFFHDJBHADABCBEBO@AAAI@EACC@GD@J@F@FAACCOECC@@AIIAE"],["@@B[@UCQGM@@@@AAIMIKMEOAUBIHGNGH@@ALIRABJ^B\\FNCRFLPAHEJGRKVIRGHA"],["@@@AD@B@@@@A@@D@DAB@@E@BACCAA@@@C@C@CAA@@D@B@BA@"]],"encodeOffsets":[[[108832,26877]],[[108913,26910]],[[108777,26658]]]}},{"type":"Feature","id":"520402107","properties":{"name":"蔡官镇","childNum":3,"cp":[105.993159,26.339172]},"geometry":{"type":"MultiPolygon","coordinates":[["@@AGECQBUBGA@OOGCKPCVDXAPIDI@@BABABAFCLEFCDEAAEAE@C@CAECCGAGBEA@@@@C@@@A@A@C@AAA@A@A@ABA@A@@@A@CA@@A@AA@@A@A@@@AAA@A@@AA@C@A@C@AA@@A@A@CA@AC@AAA@C@@@A@AAA@@@AA@AA@@A@@BA@@B@@A@AAAAACEAGACACAAC@CBCFAHAPBH@@@B@@@@@@@FABABC@A@@@AB@@A@@@@LMDOEIKGKIIGOFENEFMAGOCYC[AKCSAC@AA@@@A@CKACAAA@C@C@@AACAA@CBA@@B@GI@BCDA@A@A@A@AB@BA@@@A@@CAACI@C@CB@BAD@D@@@AE@A@CBABABA@C@CBADGAAACC@C@A@@@BA@C@AAA@E@@D@D@@@BC@C@EACAAA@AB@BAB@D@@ABA@@@@BA@ACC@A@CACAA@C@A@C@@A@@BA@@AAA@A@A@@A@A@AAE@A@C@G@EAAAAAAC@CBAB@@A@@@@B@BABA@CAABA@@E@IBEAAAAA@@A@ADCB@D@@A@C@ACAAAADAB@B@BCA@@A@A@@ABA@A@A@@C@CCAIECIBCH@L@NANATATCLIPKLOHQFKDQBOCIAGDAFEJCHEHCLGHGJQ@MAIEQGIIKKGKECAACCECAAA@@A@CAAAAEIC@A@AB@BA@ABA@C@CBAB@@AB@DBDBDA@C@A@CAA@CBAB@@@B@BADCAE@E@A@IAC@A@CACACAA@GAKAUFMAMCIGKKMAED@@A@CBC@A@@A@A@A@@AC@@@@CAE@ABBB@B@B@BABB@@@BBDBDB@@@@BB@D@BAB@@@B@B@AC@AAEAC@C@ABCBA@ABACAB@@BD@B@B@BD@DBFDEDEFCNIHE@KCQEEF@PAL@LAFEBGBKFIFIDECMCK@CDAHBHHHPFNDPHDJBPLNNLFLFRBNFLFHEDQBIDILCBEBI@K@O@AAEAKIKEOGMEEAEBED@B@@DBB@B@@BA@@BABB@B@FAB@BB@BADBB@B@BCB@@@@EB@@A@A@@AAA@AA@AA@@@@AAA@AAAAACA@@@A@A@@@@@@A@@A@@@@A@A@@AA@@CA@@A@C@C@AAC@C@GBC@@@@B@@BB@B@@@@@@AB@@@BC@CACCA@ABAB@BA@@@CBAB@@BBBBD@DBBB@@@@@@A@@@C@CAA@@ACAA@ABAB@BABA@@D@@CFAAA@@B@B@D@B@BB@@BLR@BB@BBB@BBBBDFBBFBF@RAF@B@B@BFBDBFBFDD@BNT@@@@@@B@@@@B@@DAF@FBBDBFBDJDB@@B@@BB@@@@B@@BB@@@BBB@@BB@@@@@B@@BD@@@CBAB@B@BABAD@DABAB@BEFC@ADHHFDL@VEF@BDBRAFDHHH@DCF@FDJBF@FDFDBL@FBHAFDDF@FAFEDEFBNBBLBNGFDFJFP@PCDIDKBICCFBJJNNHPBLHTFLHPNRNXPVP^XRTABABABB@BDBBBBBBB@D@B@@@@@BB@@@BB@@BB@@BDD@B@B@BBB@B@BDD@@@@BB@@BB@@@B@@@B@@@@D@D@@B@B@BC@@@A@BD@BAD@BDDBBH@D@B@BB@@@C@A@A@@@A@@@A@@@AA@@@@@DE@CAC@CFIFABCJEJ@TLRHTFNDNBN@FMBKDMFIB@@B@DBBFDDDBB@@B@D@BABCBEBKBIHAHGBGGKIOIMCMAOBGHGLBVLRNLNFJDHAL@FJHR@RGRBNEHCBEAA@GDIBEACCAE@IBCBCBCAAA@A@A@C@ACAAACA@C@CBAB@@@HAB@F@F@D@D@DA@ABGDEDAFAH@JBFBDA@C@CFAD@BAACAACBC@@ABCDABC@ACAIGACC@C@A@KFIFC@C@C@CCAA@EAEAAAA@@@@@A@@B@@@@AB@@@@@BB@@FBD@BADCBA@A@@@A@A@ABAB@@ABABA@@@A@AB@AA@C@@BA@@@@DA@@BA@E@CFAF@FDFFDFLBPNLHTJJAPGJIA@@A@@@ABEBE@A@A@@@ABABABA@@BABADCBAB@BABAB@B@@@B@BAD@B@@DB@@@@BABA@AB@B@@AB@B@BAB@BABABA@CBABA@CBBB@@@BB@@DBBB@BAFCDABA@ADABABCBAB@@@@D@D@BDBD@BAHC@AD@L@LDFFHDJBHADABCBEBO@AAAI@EACC@GD@J@F@FAACCOECC@@AIIAE"],["@@B[@UCQGM@@@@AAIMIKMEOAUBIHGNGH@@ALIRABJ^B\\FNCRFLPAHEJGRKVIRGHA"],["@@@AD@B@@@@A@@D@DAB@@E@BACCAA@@@C@C@CAA@@D@B@BA@"]],"encodeOffsets":[[[108832,26877]],[[108913,26910]],[[108777,26658]]]}},{"type":"Feature","id":"520402108","properties":{"name":"轿子山镇","childNum":3,"cp":[105.940595,26.33367]},"geometry":{"type":"MultiPolygon","coordinates":[["@@AGECQBUBGA@OOGCKPCVDXAPIDI@@BABABAFCLEFCDEAAEAE@C@CAECCGAGBEA@@@@C@@@A@A@C@AAA@A@A@ABA@A@@@A@CA@@A@AA@@A@A@@@AAA@A@@AA@C@A@C@AA@@A@A@CA@AC@AAA@C@@@A@AAA@@@AA@AA@@A@@BA@@B@@A@AAAAACEAGACACAAC@CBCFAHAPBH@@@B@@@@@@@FABABC@A@@@AB@@A@@@@LMDOEIKGKIIGOFENEFMAGOCYC[AKCSAC@AA@@@A@CKACAAA@C@C@@AACAA@CBA@@B@GI@BCDA@A@A@A@AB@BA@@@A@@CAACI@C@CB@BAD@D@@@AE@A@CBABABA@C@CBADGAAACC@C@A@@@BA@C@AAA@E@@D@D@@@BC@C@EACAAA@AB@BAB@D@@ABA@@@@BA@ACC@A@CACAA@C@A@C@@A@@BA@@AAA@A@A@@A@A@AAE@A@C@G@EAAAAAAC@CBAB@@A@@@@B@BABA@CAABA@@E@IBEAAAAA@@A@ADCB@D@@A@C@ACAAAADAB@B@BCA@@A@A@@ABA@A@A@@C@CCAIECIBCH@L@NANATATCLIPKLOHQFKDQBOCIAGDAFEJCHEHCLGHGJQ@MAIEQGIIKKGKECAACCECAAA@@A@CAAAAEIC@A@AB@BA@ABA@C@CBAB@@AB@DBDBDA@C@A@CAA@CBAB@@@B@BADCAE@E@A@IAC@A@CACACAA@GAKAUFMAMCIGKKMAED@@A@CBC@A@@A@A@A@@AC@@@@CAE@ABBB@B@B@BABB@@@BBDBDB@@@@BB@D@BAB@@@B@B@AC@AAEAC@C@ABCBA@ABACAB@@BD@B@B@BD@DBFDEDEFCNIHE@KCQEEF@PAL@LAFEBGBKFIFIDECMCK@CDAHBHHHPFNDPHDJBPLNNLFLFRBNFLFHEDQBIDILCBEBI@K@O@AAEAKIKEOGMEEAEBED@B@@DBB@B@@BA@@BABB@B@FAB@BB@BADBB@B@BCB@@@@EB@@A@A@@AAA@AA@AA@@@@AAA@AAAAACA@@@A@A@@@@@@A@@A@@@@A@A@@AA@@CA@@A@C@C@AAC@C@GBC@@@@B@@BB@B@@@@@@AB@@@BC@CACCA@ABAB@BA@@@CBAB@@BBBBD@DBBB@@@@@@A@@@C@CAA@@ACAA@ABAB@BABA@@D@@CFAAA@@B@B@D@B@BB@@BLR@BB@BBB@BBBBDFBBFBF@RAF@B@B@BFBDBFBFDD@BNT@@@@@@B@@@@B@@DAF@FBBDBFBDJDB@@B@@BB@@@@B@@BB@@@BBB@@BB@@@@@B@@BD@@@CBAB@B@BABAD@DABAB@BEFC@ADHHFDL@VEF@BDBRAFDHHH@DCF@FDJBF@FDFDBL@FBHAFDDF@FAFEDEFBNBBLBNGFDFJFP@PCDIDKBICCFBJJNNHPBLHTFLHPNRNXPVP^XRTABABABB@BDBBBBBBB@D@B@@@@@BB@@@BB@@BB@@BDD@B@B@BBB@B@BDD@@@@BB@@BB@@@B@@@B@@@@D@D@@B@B@BC@@@A@BD@BAD@BDDBBH@D@B@BB@@@C@A@A@@@A@@@A@@@AA@@@@@DE@CAC@CFIFABCJEJ@TLRHTFNDNBN@FMBKDMFIB@@B@DBBFDDDBB@@B@D@BABCBEBKBIHAHGBGGKIOIMCMAOBGHGLBVLRNLNFJDHAL@FJHR@RGRBNEHCBEAA@GDIBEACCAE@IBCBCBCAAA@A@A@C@ACAAACA@C@CBAB@@@HAB@F@F@D@D@DA@ABGDEDAFAH@JBFBDA@C@CFAD@BAACAACBC@@ABCDABC@ACAIGACC@C@A@KFIFC@C@C@CCAA@EAEAAAA@@@@@A@@B@@@@AB@@@@@BB@@FBD@BADCBA@A@@@A@A@ABAB@@ABABA@@@A@AB@AA@C@@BA@@@@DA@@BA@E@CFAF@FDFFDFLBPNLHTJJAPGJIA@@A@@@ABEBE@A@A@@@ABABABA@@BABADCBAB@BABAB@B@@@B@BAD@B@@DB@@@@BABA@AB@B@@AB@B@BAB@BABABA@CBABA@CBBB@@@BB@@DBBB@BAFCDABA@ADABABCBAB@@@@D@D@BDBD@BAHC@AD@L@LDFFHDJBHADABCBEBO@AAAI@EACC@GD@J@F@FAACCOECC@@AIIAE"],["@@B[@UCQGM@@@@AAIMIKMEOAUBIHGNGH@@ALIRABJ^B\\FNCRFLPAHEJGRKVIRGHA"],["@@@AD@B@@@@A@@D@DAB@@E@BACCAA@@@C@C@CAA@@D@B@BA@"]],"encodeOffsets":[[[108832,26877]],[[108913,26910]],[[108777,26658]]]}},{"type":"Feature","id":"520402109","properties":{"name":"旧州镇","childNum":3,"cp":[106.149039,26.255889]},"geometry":{"type":"MultiPolygon","coordinates":[["@@AGECQBUBGA@OOGCKPCVDXAPIDI@@BABABAFCLEFCDEAAEAE@C@CAECCGAGBEA@@@@C@@@A@A@C@AAA@A@A@ABA@A@@@A@CA@@A@AA@@A@A@@@AAA@A@@AA@C@A@C@AA@@A@A@CA@AC@AAA@C@@@A@AAA@@@AA@AA@@A@@BA@@B@@A@AAAAACEAGACACAAC@CBCFAHAPBH@@@B@@@@@@@FABABC@A@@@AB@@A@@@@LMDOEIKGKIIGOFENEFMAGOCYC[AKCSAC@AA@@@A@CKACAAA@C@C@@AACAA@CBA@@B@GI@BCDA@A@A@A@AB@BA@@@A@@CAACI@C@CB@BAD@D@@@AE@A@CBABABA@C@CBADGAAACC@C@A@@@BA@C@AAA@E@@D@D@@@BC@C@EACAAA@AB@BAB@D@@ABA@@@@BA@ACC@A@CACAA@C@A@C@@A@@BA@@AAA@A@A@@A@A@AAE@A@C@G@EAAAAAAC@CBAB@@A@@@@B@BABA@CAABA@@E@IBEAAAAA@@A@ADCB@D@@A@C@ACAAAADAB@B@BCA@@A@A@@ABA@A@A@@C@CCAIECIBCH@L@NANATATCLIPKLOHQFKDQBOCIAGDAFEJCHEHCLGHGJQ@MAIEQGIIKKGKECAACCECAAA@@A@CAAAAEIC@A@AB@BA@ABA@C@CBAB@@AB@DBDBDA@C@A@CAA@CBAB@@@B@BADCAE@E@A@IAC@A@CACACAA@GAKAUFMAMCIGKKMAED@@A@CBC@A@@A@A@A@@AC@@@@CAE@ABBB@B@B@BABB@@@BBDBDB@@@@BB@D@BAB@@@B@B@AC@AAEAC@C@ABCBA@ABACAB@@BD@B@B@BD@DBFDEDEFCNIHE@KCQEEF@PAL@LAFEBGBKFIFIDECMCK@CDAHBHHHPFNDPHDJBPLNNLFLFRBNFLFHEDQBIDILCBEBI@K@O@AAEAKIKEOGMEEAEBED@B@@DBB@B@@BA@@BABB@B@FAB@BB@BADBB@B@BCB@@@@EB@@A@A@@AAA@AA@AA@@@@AAA@AAAAACA@@@A@A@@@@@@A@@A@@@@A@A@@AA@@CA@@A@C@C@AAC@C@GBC@@@@B@@BB@B@@@@@@AB@@@BC@CACCA@ABAB@BA@@@CBAB@@BBBBD@DBBB@@@@@@A@@@C@CAA@@ACAA@ABAB@BABA@@D@@CFAAA@@B@B@D@B@BB@@BLR@BB@BBB@BBBBDFBBFBF@RAF@B@B@BFBDBFBFDD@BNT@@@@@@B@@@@B@@DAF@FBBDBFBDJDB@@B@@BB@@@@B@@BB@@@BBB@@BB@@@@@B@@BD@@@CBAB@B@BABAD@DABAB@BEFC@ADHHFDL@VEF@BDBRAFDHHH@DCF@FDJBF@FDFDBL@FBHAFDDF@FAFEDEFBNBBLBNGFDFJFP@PCDIDKBICCFBJJNNHPBLHTFLHPNRNXPVP^XRTABABABB@BDBBBBBBB@D@B@@@@@BB@@@BB@@BB@@BDD@B@B@BBB@B@BDD@@@@BB@@BB@@@B@@@B@@@@D@D@@B@B@BC@@@A@BD@BAD@BDDBBH@D@B@BB@@@C@A@A@@@A@@@A@@@AA@@@@@DE@CAC@CFIFABCJEJ@TLRHTFNDNBN@FMBKDMFIB@@B@DBBFDDDBB@@B@D@BABCBEBKBIHAHGBGGKIOIMCMAOBGHGLBVLRNLNFJDHAL@FJHR@RGRBNEHCBEAA@GDIBEACCAE@IBCBCBCAAA@A@A@C@ACAAACA@C@CBAB@@@HAB@F@F@D@D@DA@ABGDEDAFAH@JBFBDA@C@CFAD@BAACAACBC@@ABCDABC@ACAIGACC@C@A@KFIFC@C@C@CCAA@EAEAAAA@@@@@A@@B@@@@AB@@@@@BB@@FBD@BADCBA@A@@@A@A@ABAB@@ABABA@@@A@AB@AA@C@@BA@@@@DA@@BA@E@CFAF@FDFFDFLBPNLHTJJAPGJIA@@A@@@ABEBE@A@A@@@ABABABA@@BABADCBAB@BABAB@B@@@B@BAD@B@@DB@@@@BABA@AB@B@@AB@B@BAB@BABABA@CBABA@CBBB@@@BB@@DBBB@BAFCDABA@ADABABCBAB@@@@D@D@BDBD@BAHC@AD@L@LDFFHDJBHADABCBEBO@AAAI@EACC@GD@J@F@FAACCOECC@@AIIAE"],["@@B[@UCQGM@@@@AAIMIKMEOAUBIHGNGH@@ALIRABJ^B\\FNCRFLPAHEJGRKVIRGHA"],["@@@AD@B@@@@A@@D@DAB@@E@BACCAA@@@C@C@CAA@@D@B@BA@"]],"encodeOffsets":[[[108832,26877]],[[108913,26910]],[[108777,26658]]]}},{"type":"Feature","id":"520402200","properties":{"name":"新场布依族苗族乡","childNum":3,"cp":[105.940369,26.105462]},"geometry":{"type":"MultiPolygon","coordinates":[["@@AGECQBUBGA@OOGCKPCVDXAPIDI@@BABABAFCLEFCDEAAEAE@C@CAECCGAGBEA@@@@C@@@A@A@C@AAA@A@A@ABA@A@@@A@CA@@A@AA@@A@A@@@AAA@A@@AA@C@A@C@AA@@A@A@CA@AC@AAA@C@@@A@AAA@@@AA@AA@@A@@BA@@B@@A@AAAAACEAGACACAAC@CBCFAHAPBH@@@B@@@@@@@FABABC@A@@@AB@@A@@@@LMDOEIKGKIIGOFENEFMAGOCYC[AKCSAC@AA@@@A@CKACAAA@C@C@@AACAA@CBA@@B@GI@BCDA@A@A@A@AB@BA@@@A@@CAACI@C@CB@BAD@D@@@AE@A@CBABABA@C@CBADGAAACC@C@A@@@BA@C@AAA@E@@D@D@@@BC@C@EACAAA@AB@BAB@D@@ABA@@@@BA@ACC@A@CACAA@C@A@C@@A@@BA@@AAA@A@A@@A@A@AAE@A@C@G@EAAAAAAC@CBAB@@A@@@@B@BABA@CAABA@@E@IBEAAAAA@@A@ADCB@D@@A@C@ACAAAADAB@B@BCA@@A@A@@ABA@A@A@@C@CCAIECIBCH@L@NANATATCLIPKLOHQFKDQBOCIAGDAFEJCHEHCLGHGJQ@MAIEQGIIKKGKECAACCECAAA@@A@CAAAAEIC@A@AB@BA@ABA@C@CBAB@@AB@DBDBDA@C@A@CAA@CBAB@@@B@BADCAE@E@A@IAC@A@CACACAA@GAKAUFMAMCIGKKMAED@@A@CBC@A@@A@A@A@@AC@@@@CAE@ABBB@B@B@BABB@@@BBDBDB@@@@BB@D@BAB@@@B@B@AC@AAEAC@C@ABCBA@ABACAB@@BD@B@B@BD@DBFDEDEFCNIHE@KCQEEF@PAL@LAFEBGBKFIFIDECMCK@CDAHBHHHPFNDPHDJBPLNNLFLFRBNFLFHEDQBIDILCBEBI@K@O@AAEAKIKEOGMEEAEBED@B@@DBB@B@@BA@@BABB@B@FAB@BB@BADBB@B@BCB@@@@EB@@A@A@@AAA@AA@AA@@@@AAA@AAAAACA@@@A@A@@@@@@A@@A@@@@A@A@@AA@@CA@@A@C@C@AAC@C@GBC@@@@B@@BB@B@@@@@@AB@@@BC@CACCA@ABAB@BA@@@CBAB@@BBBBD@DBBB@@@@@@A@@@C@CAA@@ACAA@ABAB@BABA@@D@@CFAAA@@B@B@D@B@BB@@BLR@BB@BBB@BBBBDFBBFBF@RAF@B@B@BFBDBFBFDD@BNT@@@@@@B@@@@B@@DAF@FBBDBFBDJDB@@B@@BB@@@@B@@BB@@@BBB@@BB@@@@@B@@BD@@@CBAB@B@BABAD@DABAB@BEFC@ADHHFDL@VEF@BDBRAFDHHH@DCF@FDJBF@FDFDBL@FBHAFDDF@FAFEDEFBNBBLBNGFDFJFP@PCDIDKBICCFBJJNNHPBLHTFLHPNRNXPVP^XRTABABABB@BDBBBBBBB@D@B@@@@@BB@@@BB@@BB@@BDD@B@B@BBB@B@BDD@@@@BB@@BB@@@B@@@B@@@@D@D@@B@B@BC@@@A@BD@BAD@BDDBBH@D@B@BB@@@C@A@A@@@A@@@A@@@AA@@@@@DE@CAC@CFIFABCJEJ@TLRHTFNDNBN@FMBKDMFIB@@B@DBBFDDDBB@@B@D@BABCBEBKBIHAHGBGGKIOIMCMAOBGHGLBVLRNLNFJDHAL@FJHR@RGRBNEHCBEAA@GDIBEACCAE@IBCBCBCAAA@A@A@C@ACAAACA@C@CBAB@@@HAB@F@F@D@D@DA@ABGDEDAFAH@JBFBDA@C@CFAD@BAACAACBC@@ABCDABC@ACAIGACC@C@A@KFIFC@C@C@CCAA@EAEAAAA@@@@@A@@B@@@@AB@@@@@BB@@FBD@BADCBA@A@@@A@A@ABAB@@ABABA@@@A@AB@AA@C@@BA@@@@DA@@BA@E@CFAF@FDFFDFLBPNLHTJJAPGJIA@@A@@@ABEBE@A@A@@@ABABABA@@BABADCBAB@BABAB@B@@@B@BAD@B@@DB@@@@BABA@AB@B@@AB@B@BAB@BABABA@CBABA@CBBB@@@BB@@DBBB@BAFCDABA@ADABABCBAB@@@@D@D@BDBD@BAHC@AD@L@LDFFHDJBHADABCBEBO@AAAI@EACC@GD@J@F@FAACCOECC@@AIIAE"],["@@B[@UCQGM@@@@AAIMIKMEOAUBIHGNGH@@ALIRABJ^B\\FNCRFLPAHEJGRKVIRGHA"],["@@@AD@B@@@@A@@D@DAB@@E@BACCAA@@@C@C@CAA@@D@B@BA@"]],"encodeOffsets":[[[108832,26877]],[[108913,26910]],[[108777,26658]]]}},{"type":"Feature","id":"520402201","properties":{"name":"岩腊苗族布依族乡","childNum":3,"cp":[105.97328,26.043133]},"geometry":{"type":"MultiPolygon","coordinates":[["@@AGECQBUBGA@OOGCKPCVDXAPIDI@@BABABAFCLEFCDEAAEAE@C@CAECCGAGBEA@@@@C@@@A@A@C@AAA@A@A@ABA@A@@@A@CA@@A@AA@@A@A@@@AAA@A@@AA@C@A@C@AA@@A@A@CA@AC@AAA@C@@@A@AAA@@@AA@AA@@A@@BA@@B@@A@AAAAACEAGACACAAC@CBCFAHAPBH@@@B@@@@@@@FABABC@A@@@AB@@A@@@@LMDOEIKGKIIGOFENEFMAGOCYC[AKCSAC@AA@@@A@CKACAAA@C@C@@AACAA@CBA@@B@GI@BCDA@A@A@A@AB@BA@@@A@@CAACI@C@CB@BAD@D@@@AE@A@CBABABA@C@CBADGAAACC@C@A@@@BA@C@AAA@E@@D@D@@@BC@C@EACAAA@AB@BAB@D@@ABA@@@@BA@ACC@A@CACAA@C@A@C@@A@@BA@@AAA@A@A@@A@A@AAE@A@C@G@EAAAAAAC@CBAB@@A@@@@B@BABA@CAABA@@E@IBEAAAAA@@A@ADCB@D@@A@C@ACAAAADAB@B@BCA@@A@A@@ABA@A@A@@C@CCAIECIBCH@L@NANATATCLIPKLOHQFKDQBOCIAGDAFEJCHEHCLGHGJQ@MAIEQGIIKKGKECAACCECAAA@@A@CAAAAEIC@A@AB@BA@ABA@C@CBAB@@AB@DBDBDA@C@A@CAA@CBAB@@@B@BADCAE@E@A@IAC@A@CACACAA@GAKAUFMAMCIGKKMAED@@A@CBC@A@@A@A@A@@AC@@@@CAE@ABBB@B@B@BABB@@@BBDBDB@@@@BB@D@BAB@@@B@B@AC@AAEAC@C@ABCBA@ABACAB@@BD@B@B@BD@DBFDEDEFCNIHE@KCQEEF@PAL@LAFEBGBKFIFIDECMCK@CDAHBHHHPFNDPHDJBPLNNLFLFRBNFLFHEDQBIDILCBEBI@K@O@AAEAKIKEOGMEEAEBED@B@@DBB@B@@BA@@BABB@B@FAB@BB@BADBB@B@BCB@@@@EB@@A@A@@AAA@AA@AA@@@@AAA@AAAAACA@@@A@A@@@@@@A@@A@@@@A@A@@AA@@CA@@A@C@C@AAC@C@GBC@@@@B@@BB@B@@@@@@AB@@@BC@CACCA@ABAB@BA@@@CBAB@@BBBBD@DBBB@@@@@@A@@@C@CAA@@ACAA@ABAB@BABA@@D@@CFAAA@@B@B@D@B@BB@@BLR@BB@BBB@BBBBDFBBFBF@RAF@B@B@BFBDBFBFDD@BNT@@@@@@B@@@@B@@DAF@FBBDBFBDJDB@@B@@BB@@@@B@@BB@@@BBB@@BB@@@@@B@@BD@@@CBAB@B@BABAD@DABAB@BEFC@ADHHFDL@VEF@BDBRAFDHHH@DCF@FDJBF@FDFDBL@FBHAFDDF@FAFEDEFBNBBLBNGFDFJFP@PCDIDKBICCFBJJNNHPBLHTFLHPNRNXPVP^XRTABABABB@BDBBBBBBB@D@B@@@@@BB@@@BB@@BB@@BDD@B@B@BBB@B@BDD@@@@BB@@BB@@@B@@@B@@@@D@D@@B@B@BC@@@A@BD@BAD@BDDBBH@D@B@BB@@@C@A@A@@@A@@@A@@@AA@@@@@DE@CAC@CFIFABCJEJ@TLRHTFNDNBN@FMBKDMFIB@@B@DBBFDDDBB@@B@D@BABCBEBKBIHAHGBGGKIOIMCMAOBGHGLBVLRNLNFJDHAL@FJHR@RGRBNEHCBEAA@GDIBEACCAE@IBCBCBCAAA@A@A@C@ACAAACA@C@CBAB@@@HAB@F@F@D@D@DA@ABGDEDAFAH@JBFBDA@C@CFAD@BAACAACBC@@ABCDABC@ACAIGACC@C@A@KFIFC@C@C@CCAA@EAEAAAA@@@@@A@@B@@@@AB@@@@@BB@@FBD@BADCBA@A@@@A@A@ABAB@@ABABA@@@A@AB@AA@C@@BA@@@@DA@@BA@E@CFAF@FDFFDFLBPNLHTJJAPGJIA@@A@@@ABEBE@A@A@@@ABABABA@@BABADCBAB@BABAB@B@@@B@BAD@B@@DB@@@@BABA@AB@B@@AB@B@BAB@BABABA@CBABA@CBBB@@@BB@@DBBB@BAFCDABA@ADABABCBAB@@@@D@D@BDBD@BAHC@AD@L@LDFFHDJBHADABCBEBO@AAAI@EACC@GD@J@F@FAACCOECC@@AIIAE"],["@@B[@UCQGM@@@@AAIMIKMEOAUBIHGNGH@@ALIRABJ^B\\FNCRFLPAHEJGRKVIRGHA"],["@@@AD@B@@@@A@@D@DAB@@E@BACCAA@@@C@C@CAA@@D@B@BA@"]],"encodeOffsets":[[[108832,26877]],[[108913,26910]],[[108777,26658]]]}},{"type":"Feature","id":"520402202","properties":{"name":"鸡场布依族苗族乡","childNum":3,"cp":[106.091395,26.058241]},"geometry":{"type":"MultiPolygon","coordinates":[["@@AGECQBUBGA@OOGCKPCVDXAPIDI@@BABABAFCLEFCDEAAEAE@C@CAECCGAGBEA@@@@C@@@A@A@C@AAA@A@A@ABA@A@@@A@CA@@A@AA@@A@A@@@AAA@A@@AA@C@A@C@AA@@A@A@CA@AC@AAA@C@@@A@AAA@@@AA@AA@@A@@BA@@B@@A@AAAAACEAGACACAAC@CBCFAHAPBH@@@B@@@@@@@FABABC@A@@@AB@@A@@@@LMDOEIKGKIIGOFENEFMAGOCYC[AKCSAC@AA@@@A@CKACAAA@C@C@@AACAA@CBA@@B@GI@BCDA@A@A@A@AB@BA@@@A@@CAACI@C@CB@BAD@D@@@AE@A@CBABABA@C@CBADGAAACC@C@A@@@BA@C@AAA@E@@D@D@@@BC@C@EACAAA@AB@BAB@D@@ABA@@@@BA@ACC@A@CACAA@C@A@C@@A@@BA@@AAA@A@A@@A@A@AAE@A@C@G@EAAAAAAC@CBAB@@A@@@@B@BABA@CAABA@@E@IBEAAAAA@@A@ADCB@D@@A@C@ACAAAADAB@B@BCA@@A@A@@ABA@A@A@@C@CCAIECIBCH@L@NANATATCLIPKLOHQFKDQBOCIAGDAFEJCHEHCLGHGJQ@MAIEQGIIKKGKECAACCECAAA@@A@CAAAAEIC@A@AB@BA@ABA@C@CBAB@@AB@DBDBDA@C@A@CAA@CBAB@@@B@BADCAE@E@A@IAC@A@CACACAA@GAKAUFMAMCIGKKMAED@@A@CBC@A@@A@A@A@@AC@@@@CAE@ABBB@B@B@BABB@@@BBDBDB@@@@BB@D@BAB@@@B@B@AC@AAEAC@C@ABCBA@ABACAB@@BD@B@B@BD@DBFDEDEFCNIHE@KCQEEF@PAL@LAFEBGBKFIFIDECMCK@CDAHBHHHPFNDPHDJBPLNNLFLFRBNFLFHEDQBIDILCBEBI@K@O@AAEAKIKEOGMEEAEBED@B@@DBB@B@@BA@@BABB@B@FAB@BB@BADBB@B@BCB@@@@EB@@A@A@@AAA@AA@AA@@@@AAA@AAAAACA@@@A@A@@@@@@A@@A@@@@A@A@@AA@@CA@@A@C@C@AAC@C@GBC@@@@B@@BB@B@@@@@@AB@@@BC@CACCA@ABAB@BA@@@CBAB@@BBBBD@DBBB@@@@@@A@@@C@CAA@@ACAA@ABAB@BABA@@D@@CFAAA@@B@B@D@B@BB@@BLR@BB@BBB@BBBBDFBBFBF@RAF@B@B@BFBDBFBFDD@BNT@@@@@@B@@@@B@@DAF@FBBDBFBDJDB@@B@@BB@@@@B@@BB@@@BBB@@BB@@@@@B@@BD@@@CBAB@B@BABAD@DABAB@BEFC@ADHHFDL@VEF@BDBRAFDHHH@DCF@FDJBF@FDFDBL@FBHAFDDF@FAFEDEFBNBBLBNGFDFJFP@PCDIDKBICCFBJJNNHPBLHTFLHPNRNXPVP^XRTABABABB@BDBBBBBBB@D@B@@@@@BB@@@BB@@BB@@BDD@B@B@BBB@B@BDD@@@@BB@@BB@@@B@@@B@@@@D@D@@B@B@BC@@@A@BD@BAD@BDDBBH@D@B@BB@@@C@A@A@@@A@@@A@@@AA@@@@@DE@CAC@CFIFABCJEJ@TLRHTFNDNBN@FMBKDMFIB@@B@DBBFDDDBB@@B@D@BABCBEBKBIHAHGBGGKIOIMCMAOBGHGLBVLRNLNFJDHAL@FJHR@RGRBNEHCBEAA@GDIBEACCAE@IBCBCBCAAA@A@A@C@ACAAACA@C@CBAB@@@HAB@F@F@D@D@DA@ABGDEDAFAH@JBFBDA@C@CFAD@BAACAACBC@@ABCDABC@ACAIGACC@C@A@KFIFC@C@C@CCAA@EAEAAAA@@@@@A@@B@@@@AB@@@@@BB@@FBD@BADCBA@A@@@A@A@ABAB@@ABABA@@@A@AB@AA@C@@BA@@@@DA@@BA@E@CFAF@FDFFDFLBPNLHTJJAPGJIA@@A@@@ABEBE@A@A@@@ABABABA@@BABADCBAB@BABAB@B@@@B@BAD@B@@DB@@@@BABA@AB@B@@AB@B@BAB@BABABA@CBABA@CBBB@@@BB@@DBBB@BAFCDABA@ADABABCBAB@@@@D@D@BDBD@BAHC@AD@L@LDFFHDJBHADABCBEBO@AAAI@EACC@GD@J@F@FAACCOECC@@AIIAE"],["@@B[@UCQGM@@@@AAIMIKMEOAUBIHGNGH@@ALIRABJ^B\\FNCRFLPAHEJGRKVIRGHA"],["@@@AD@B@@@@A@@D@DAB@@E@BACCAA@@@C@C@CAA@@D@B@BA@"]],"encodeOffsets":[[[108832,26877]],[[108913,26910]],[[108777,26658]]]}},{"type":"Feature","id":"520402203","properties":{"name":"杨武布依族苗族乡","childNum":3,"cp":[106.191338,26.052004]},"geometry":{"type":"MultiPolygon","coordinates":[["@@AGECQBUBGA@OOGCKPCVDXAPIDI@@BABABAFCLEFCDEAAEAE@C@CAECCGAGBEA@@@@C@@@A@A@C@AAA@A@A@ABA@A@@@A@CA@@A@AA@@A@A@@@AAA@A@@AA@C@A@C@AA@@A@A@CA@AC@AAA@C@@@A@AAA@@@AA@AA@@A@@BA@@B@@A@AAAAACEAGACACAAC@CBCFAHAPBH@@@B@@@@@@@FABABC@A@@@AB@@A@@@@LMDOEIKGKIIGOFENEFMAGOCYC[AKCSAC@AA@@@A@CKACAAA@C@C@@AACAA@CBA@@B@GI@BCDA@A@A@A@AB@BA@@@A@@CAACI@C@CB@BAD@D@@@AE@A@CBABABA@C@CBADGAAACC@C@A@@@BA@C@AAA@E@@D@D@@@BC@C@EACAAA@AB@BAB@D@@ABA@@@@BA@ACC@A@CACAA@C@A@C@@A@@BA@@AAA@A@A@@A@A@AAE@A@C@G@EAAAAAAC@CBAB@@A@@@@B@BABA@CAABA@@E@IBEAAAAA@@A@ADCB@D@@A@C@ACAAAADAB@B@BCA@@A@A@@ABA@A@A@@C@CCAIECIBCH@L@NANATATCLIPKLOHQFKDQBOCIAGDAFEJCHEHCLGHGJQ@MAIEQGIIKKGKECAACCECAAA@@A@CAAAAEIC@A@AB@BA@ABA@C@CBAB@@AB@DBDBDA@C@A@CAA@CBAB@@@B@BADCAE@E@A@IAC@A@CACACAA@GAKAUFMAMCIGKKMAED@@A@CBC@A@@A@A@A@@AC@@@@CAE@ABBB@B@B@BABB@@@BBDBDB@@@@BB@D@BAB@@@B@B@AC@AAEAC@C@ABCBA@ABACAB@@BD@B@B@BD@DBFDEDEFCNIHE@KCQEEF@PAL@LAFEBGBKFIFIDECMCK@CDAHBHHHPFNDPHDJBPLNNLFLFRBNFLFHEDQBIDILCBEBI@K@O@AAEAKIKEOGMEEAEBED@B@@DBB@B@@BA@@BABB@B@FAB@BB@BADBB@B@BCB@@@@EB@@A@A@@AAA@AA@AA@@@@AAA@AAAAACA@@@A@A@@@@@@A@@A@@@@A@A@@AA@@CA@@A@C@C@AAC@C@GBC@@@@B@@BB@B@@@@@@AB@@@BC@CACCA@ABAB@BA@@@CBAB@@BBBBD@DBBB@@@@@@A@@@C@CAA@@ACAA@ABAB@BABA@@D@@CFAAA@@B@B@D@B@BB@@BLR@BB@BBB@BBBBDFBBFBF@RAF@B@B@BFBDBFBFDD@BNT@@@@@@B@@@@B@@DAF@FBBDBFBDJDB@@B@@BB@@@@B@@BB@@@BBB@@BB@@@@@B@@BD@@@CBAB@B@BABAD@DABAB@BEFC@ADHHFDL@VEF@BDBRAFDHHH@DCF@FDJBF@FDFDBL@FBHAFDDF@FAFEDEFBNBBLBNGFDFJFP@PCDIDKBICCFBJJNNHPBLHTFLHPNRNXPVP^XRTABABABB@BDBBBBBBB@D@B@@@@@BB@@@BB@@BB@@BDD@B@B@BBB@B@BDD@@@@BB@@BB@@@B@@@B@@@@D@D@@B@B@BC@@@A@BD@BAD@BDDBBH@D@B@BB@@@C@A@A@@@A@@@A@@@AA@@@@@DE@CAC@CFIFABCJEJ@TLRHTFNDNBN@FMBKDMFIB@@B@DBBFDDDBB@@B@D@BABCBEBKBIHAHGBGGKIOIMCMAOBGHGLBVLRNLNFJDHAL@FJHR@RGRBNEHCBEAA@GDIBEACCAE@IBCBCBCAAA@A@A@C@ACAAACA@C@CBAB@@@HAB@F@F@D@D@DA@ABGDEDAFAH@JBFBDA@C@CFAD@BAACAACBC@@ABCDABC@ACAIGACC@C@A@KFIFC@C@C@CCAA@EAEAAAA@@@@@A@@B@@@@AB@@@@@BB@@FBD@BADCBA@A@@@A@A@ABAB@@ABABA@@@A@AB@AA@C@@BA@@@@DA@@BA@E@CFAF@FDFFDFLBPNLHTJJAPGJIA@@A@@@ABEBE@A@A@@@ABABABA@@BABADCBAB@BABAB@B@@@B@BAD@B@@DB@@@@BABA@AB@B@@AB@B@BAB@BABABA@CBABA@CBBB@@@BB@@DBBB@BAFCDABA@ADABABCBAB@@@@D@D@BDBD@BAHC@AD@L@LDFFHDJBHADABCBEBO@AAAI@EACC@GD@J@F@FAACCOECC@@AIIAE"],["@@B[@UCQGM@@@@AAIMIKMEOAUBIHGNGH@@ALIRABJ^B\\FNCRFLPAHEJGRKVIRGHA"],["@@@AD@B@@@@A@@D@DAB@@E@BACCAA@@@C@C@CAA@@D@B@BA@"]],"encodeOffsets":[[[108832,26877]],[[108913,26910]],[[108777,26658]]]}},{"type":"Feature","id":"520402204","properties":{"name":"东屯乡","childNum":3,"cp":[106.236422,26.212635]},"geometry":{"type":"MultiPolygon","coordinates":[["@@AGECQBUBGA@OOGCKPCVDXAPIDI@@BABABAFCLEFCDEAAEAE@C@CAECCGAGBEA@@@@C@@@A@A@C@AAA@A@A@ABA@A@@@A@CA@@A@AA@@A@A@@@AAA@A@@AA@C@A@C@AA@@A@A@CA@AC@AAA@C@@@A@AAA@@@AA@AA@@A@@BA@@B@@A@AAAAACEAGACACAAC@CBCFAHAPBH@@@B@@@@@@@FABABC@A@@@AB@@A@@@@LMDOEIKGKIIGOFENEFMAGOCYC[AKCSAC@AA@@@A@CKACAAA@C@C@@AACAA@CBA@@B@GI@BCDA@A@A@A@AB@BA@@@A@@CAACI@C@CB@BAD@D@@@AE@A@CBABABA@C@CBADGAAACC@C@A@@@BA@C@AAA@E@@D@D@@@BC@C@EACAAA@AB@BAB@D@@ABA@@@@BA@ACC@A@CACAA@C@A@C@@A@@BA@@AAA@A@A@@A@A@AAE@A@C@G@EAAAAAAC@CBAB@@A@@@@B@BABA@CAABA@@E@IBEAAAAA@@A@ADCB@D@@A@C@ACAAAADAB@B@BCA@@A@A@@ABA@A@A@@C@CCAIECIBCH@L@NANATATCLIPKLOHQFKDQBOCIAGDAFEJCHEHCLGHGJQ@MAIEQGIIKKGKECAACCECAAA@@A@CAAAAEIC@A@AB@BA@ABA@C@CBAB@@AB@DBDBDA@C@A@CAA@CBAB@@@B@BADCAE@E@A@IAC@A@CACACAA@GAKAUFMAMCIGKKMAED@@A@CBC@A@@A@A@A@@AC@@@@CAE@ABBB@B@B@BABB@@@BBDBDB@@@@BB@D@BAB@@@B@B@AC@AAEAC@C@ABCBA@ABACAB@@BD@B@B@BD@DBFDEDEFCNIHE@KCQEEF@PAL@LAFEBGBKFIFIDECMCK@CDAHBHHHPFNDPHDJBPLNNLFLFRBNFLFHEDQBIDILCBEBI@K@O@AAEAKIKEOGMEEAEBED@B@@DBB@B@@BA@@BABB@B@FAB@BB@BADBB@B@BCB@@@@EB@@A@A@@AAA@AA@AA@@@@AAA@AAAAACA@@@A@A@@@@@@A@@A@@@@A@A@@AA@@CA@@A@C@C@AAC@C@GBC@@@@B@@BB@B@@@@@@AB@@@BC@CACCA@ABAB@BA@@@CBAB@@BBBBD@DBBB@@@@@@A@@@C@CAA@@ACAA@ABAB@BABA@@D@@CFAAA@@B@B@D@B@BB@@BLR@BB@BBB@BBBBDFBBFBF@RAF@B@B@BFBDBFBFDD@BNT@@@@@@B@@@@B@@DAF@FBBDBFBDJDB@@B@@BB@@@@B@@BB@@@BBB@@BB@@@@@B@@BD@@@CBAB@B@BABAD@DABAB@BEFC@ADHHFDL@VEF@BDBRAFDHHH@DCF@FDJBF@FDFDBL@FBHAFDDF@FAFEDEFBNBBLBNGFDFJFP@PCDIDKBICCFBJJNNHPBLHTFLHPNRNXPVP^XRTABABABB@BDBBBBBBB@D@B@@@@@BB@@@BB@@BB@@BDD@B@B@BBB@B@BDD@@@@BB@@BB@@@B@@@B@@@@D@D@@B@B@BC@@@A@BD@BAD@BDDBBH@D@B@BB@@@C@A@A@@@A@@@A@@@AA@@@@@DE@CAC@CFIFABCJEJ@TLRHTFNDNBN@FMBKDMFIB@@B@DBBFDDDBB@@B@D@BABCBEBKBIHAHGBGGKIOIMCMAOBGHGLBVLRNLNFJDHAL@FJHR@RGRBNEHCBEAA@GDIBEACCAE@IBCBCBCAAA@A@A@C@ACAAACA@C@CBAB@@@HAB@F@F@D@D@DA@ABGDEDAFAH@JBFBDA@C@CFAD@BAACAACBC@@ABCDABC@ACAIGACC@C@A@KFIFC@C@C@CCAA@EAEAAAA@@@@@A@@B@@@@AB@@@@@BB@@FBD@BADCBA@A@@@A@A@ABAB@@ABABA@@@A@AB@AA@C@@BA@@@@DA@@BA@E@CFAF@FDFFDFLBPNLHTJJAPGJIA@@A@@@ABEBE@A@A@@@ABABABA@@BABADCBAB@BABAB@B@@@B@BAD@B@@DB@@@@BABA@AB@B@@AB@B@BAB@BABABA@CBABA@CBBB@@@BB@@DBBB@BAFCDABA@ADABABCBAB@@@@D@D@BDBD@BAHC@AD@L@LDFFHDJBHADABCBEBO@AAAI@EACC@GD@J@F@FAACCOECC@@AIIAE"],["@@B[@UCQGM@@@@AAIMIKMEOAUBIHGNGH@@ALIRABJ^B\\FNCRFLPAHEJGRKVIRGHA"],["@@@AD@B@@@@A@@D@DAB@@E@BACCAA@@@C@C@CAA@@D@B@BA@"]],"encodeOffsets":[[[108832,26877]],[[108913,26910]],[[108777,26658]]]}},{"type":"Feature","id":"520402205","properties":{"name":"黄腊布依族苗族乡","childNum":3,"cp":[106.2476,26.284281]},"geometry":{"type":"MultiPolygon","coordinates":[["@@AGECQBUBGA@OOGCKPCVDXAPIDI@@BABABAFCLEFCDEAAEAE@C@CAECCGAGBEA@@@@C@@@A@A@C@AAA@A@A@ABA@A@@@A@CA@@A@AA@@A@A@@@AAA@A@@AA@C@A@C@AA@@A@A@CA@AC@AAA@C@@@A@AAA@@@AA@AA@@A@@BA@@B@@A@AAAAACEAGACACAAC@CBCFAHAPBH@@@B@@@@@@@FABABC@A@@@AB@@A@@@@LMDOEIKGKIIGOFENEFMAGOCYC[AKCSAC@AA@@@A@CKACAAA@C@C@@AACAA@CBA@@B@GI@BCDA@A@A@A@AB@BA@@@A@@CAACI@C@CB@BAD@D@@@AE@A@CBABABA@C@CBADGAAACC@C@A@@@BA@C@AAA@E@@D@D@@@BC@C@EACAAA@AB@BAB@D@@ABA@@@@BA@ACC@A@CACAA@C@A@C@@A@@BA@@AAA@A@A@@A@A@AAE@A@C@G@EAAAAAAC@CBAB@@A@@@@B@BABA@CAABA@@E@IBEAAAAA@@A@ADCB@D@@A@C@ACAAAADAB@B@BCA@@A@A@@ABA@A@A@@C@CCAIECIBCH@L@NANATATCLIPKLOHQFKDQBOCIAGDAFEJCHEHCLGHGJQ@MAIEQGIIKKGKECAACCECAAA@@A@CAAAAEIC@A@AB@BA@ABA@C@CBAB@@AB@DBDBDA@C@A@CAA@CBAB@@@B@BADCAE@E@A@IAC@A@CACACAA@GAKAUFMAMCIGKKMAED@@A@CBC@A@@A@A@A@@AC@@@@CAE@ABBB@B@B@BABB@@@BBDBDB@@@@BB@D@BAB@@@B@B@AC@AAEAC@C@ABCBA@ABACAB@@BD@B@B@BD@DBFDEDEFCNIHE@KCQEEF@PAL@LAFEBGBKFIFIDECMCK@CDAHBHHHPFNDPHDJBPLNNLFLFRBNFLFHEDQBIDILCBEBI@K@O@AAEAKIKEOGMEEAEBED@B@@DBB@B@@BA@@BABB@B@FAB@BB@BADBB@B@BCB@@@@EB@@A@A@@AAA@AA@AA@@@@AAA@AAAAACA@@@A@A@@@@@@A@@A@@@@A@A@@AA@@CA@@A@C@C@AAC@C@GBC@@@@B@@BB@B@@@@@@AB@@@BC@CACCA@ABAB@BA@@@CBAB@@BBBBD@DBBB@@@@@@A@@@C@CAA@@ACAA@ABAB@BABA@@D@@CFAAA@@B@B@D@B@BB@@BLR@BB@BBB@BBBBDFBBFBF@RAF@B@B@BFBDBFBFDD@BNT@@@@@@B@@@@B@@DAF@FBBDBFBDJDB@@B@@BB@@@@B@@BB@@@BBB@@BB@@@@@B@@BD@@@CBAB@B@BABAD@DABAB@BEFC@ADHHFDL@VEF@BDBRAFDHHH@DCF@FDJBF@FDFDBL@FBHAFDDF@FAFEDEFBNBBLBNGFDFJFP@PCDIDKBICCFBJJNNHPBLHTFLHPNRNXPVP^XRTABABABB@BDBBBBBBB@D@B@@@@@BB@@@BB@@BB@@BDD@B@B@BBB@B@BDD@@@@BB@@BB@@@B@@@B@@@@D@D@@B@B@BC@@@A@BD@BAD@BDDBBH@D@B@BB@@@C@A@A@@@A@@@A@@@AA@@@@@DE@CAC@CFIFABCJEJ@TLRHTFNDNBN@FMBKDMFIB@@B@DBBFDDDBB@@B@D@BABCBEBKBIHAHGBGGKIOIMCMAOBGHGLBVLRNLNFJDHAL@FJHR@RGRBNEHCBEAA@GDIBEACCAE@IBCBCBCAAA@A@A@C@ACAAACA@C@CBAB@@@HAB@F@F@D@D@DA@ABGDEDAFAH@JBFBDA@C@CFAD@BAACAACBC@@ABCDABC@ACAIGACC@C@A@KFIFC@C@C@CCAA@EAEAAAA@@@@@A@@B@@@@AB@@@@@BB@@FBD@BADCBA@A@@@A@A@ABAB@@ABABA@@@A@AB@AA@C@@BA@@@@DA@@BA@E@CFAF@FDFFDFLBPNLHTJJAPGJIA@@A@@@ABEBE@A@A@@@ABABABA@@BABADCBAB@BABAB@B@@@B@BAD@B@@DB@@@@BABA@AB@B@@AB@B@BAB@BABABA@CBABA@CBBB@@@BB@@DBBB@BAFCDABA@ADABABCBAB@@@@D@D@BDBD@BAHC@AD@L@LDFFHDJBHADABCBEBO@AAAI@EACC@GD@J@F@FAACCOECC@@AIIAE"],["@@B[@UCQGM@@@@AAIMIKMEOAUBIHGNGH@@ALIRABJ^B\\FNCRFLPAHEJGRKVIRGHA"],["@@@AD@B@@@@A@@D@DAB@@E@BACCAA@@@C@C@CAA@@D@B@BA@"]],"encodeOffsets":[[[108832,26877]],[[108913,26910]],[[108777,26658]]]}},{"type":"Feature","id":"520402206","properties":{"name":"刘官乡","childNum":3,"cp":[106.212708,26.271895]},"geometry":{"type":"MultiPolygon","coordinates":[["@@AGECQBUBGA@OOGCKPCVDXAPIDI@@BABABAFCLEFCDEAAEAE@C@CAECCGAGBEA@@@@C@@@A@A@C@AAA@A@A@ABA@A@@@A@CA@@A@AA@@A@A@@@AAA@A@@AA@C@A@C@AA@@A@A@CA@AC@AAA@C@@@A@AAA@@@AA@AA@@A@@BA@@B@@A@AAAAACEAGACACAAC@CBCFAHAPBH@@@B@@@@@@@FABABC@A@@@AB@@A@@@@LMDOEIKGKIIGOFENEFMAGOCYC[AKCSAC@AA@@@A@CKACAAA@C@C@@AACAA@CBA@@B@GI@BCDA@A@A@A@AB@BA@@@A@@CAACI@C@CB@BAD@D@@@AE@A@CBABABA@C@CBADGAAACC@C@A@@@BA@C@AAA@E@@D@D@@@BC@C@EACAAA@AB@BAB@D@@ABA@@@@BA@ACC@A@CACAA@C@A@C@@A@@BA@@AAA@A@A@@A@A@AAE@A@C@G@EAAAAAAC@CBAB@@A@@@@B@BABA@CAABA@@E@IBEAAAAA@@A@ADCB@D@@A@C@ACAAAADAB@B@BCA@@A@A@@ABA@A@A@@C@CCAIECIBCH@L@NANATATCLIPKLOHQFKDQBOCIAGDAFEJCHEHCLGHGJQ@MAIEQGIIKKGKECAACCECAAA@@A@CAAAAEIC@A@AB@BA@ABA@C@CBAB@@AB@DBDBDA@C@A@CAA@CBAB@@@B@BADCAE@E@A@IAC@A@CACACAA@GAKAUFMAMCIGKKMAED@@A@CBC@A@@A@A@A@@AC@@@@CAE@ABBB@B@B@BABB@@@BBDBDB@@@@BB@D@BAB@@@B@B@AC@AAEAC@C@ABCBA@ABACAB@@BD@B@B@BD@DBFDEDEFCNIHE@KCQEEF@PAL@LAFEBGBKFIFIDECMCK@CDAHBHHHPFNDPHDJBPLNNLFLFRBNFLFHEDQBIDILCBEBI@K@O@AAEAKIKEOGMEEAEBED@B@@DBB@B@@BA@@BABB@B@FAB@BB@BADBB@B@BCB@@@@EB@@A@A@@AAA@AA@AA@@@@AAA@AAAAACA@@@A@A@@@@@@A@@A@@@@A@A@@AA@@CA@@A@C@C@AAC@C@GBC@@@@B@@BB@B@@@@@@AB@@@BC@CACCA@ABAB@BA@@@CBAB@@BBBBD@DBBB@@@@@@A@@@C@CAA@@ACAA@ABAB@BABA@@D@@CFAAA@@B@B@D@B@BB@@BLR@BB@BBB@BBBBDFBBFBF@RAF@B@B@BFBDBFBFDD@BNT@@@@@@B@@@@B@@DAF@FBBDBFBDJDB@@B@@BB@@@@B@@BB@@@BBB@@BB@@@@@B@@BD@@@CBAB@B@BABAD@DABAB@BEFC@ADHHFDL@VEF@BDBRAFDHHH@DCF@FDJBF@FDFDBL@FBHAFDDF@FAFEDEFBNBBLBNGFDFJFP@PCDIDKBICCFBJJNNHPBLHTFLHPNRNXPVP^XRTABABABB@BDBBBBBBB@D@B@@@@@BB@@@BB@@BB@@BDD@B@B@BBB@B@BDD@@@@BB@@BB@@@B@@@B@@@@D@D@@B@B@BC@@@A@BD@BAD@BDDBBH@D@B@BB@@@C@A@A@@@A@@@A@@@AA@@@@@DE@CAC@CFIFABCJEJ@TLRHTFNDNBN@FMBKDMFIB@@B@DBBFDDDBB@@B@D@BABCBEBKBIHAHGBGGKIOIMCMAOBGHGLBVLRNLNFJDHAL@FJHR@RGRBNEHCBEAA@GDIBEACCAE@IBCBCBCAAA@A@A@C@ACAAACA@C@CBAB@@@HAB@F@F@D@D@DA@ABGDEDAFAH@JBFBDA@C@CFAD@BAACAACBC@@ABCDABC@ACAIGACC@C@A@KFIFC@C@C@CCAA@EAEAAAA@@@@@A@@B@@@@AB@@@@@BB@@FBD@BADCBA@A@@@A@A@ABAB@@ABABA@@@A@AB@AA@C@@BA@@@@DA@@BA@E@CFAF@FDFFDFLBPNLHTJJAPGJIA@@A@@@ABEBE@A@A@@@ABABABA@@BABADCBAB@BABAB@B@@@B@BAD@B@@DB@@@@BABA@AB@B@@AB@B@BAB@BABABA@CBABA@CBBB@@@BB@@DBBB@BAFCDABA@ADABABCBAB@@@@D@D@BDBD@BAHC@AD@L@LDFFHDJBHADABCBEBO@AAAI@EACC@GD@J@F@FAACCOECC@@AIIAE"],["@@B[@UCQGM@@@@AAIMIKMEOAUBIHGNGH@@ALIRABJ^B\\FNCRFLPAHEJGRKVIRGHA"],["@@@AD@B@@@@A@@D@DAB@@E@BACCAA@@@C@C@CAA@@D@B@BA@"]],"encodeOffsets":[[[108832,26877]],[[108913,26910]],[[108777,26658]]]}}]}